[{"blue": {"id": 134408, "name": "BeFive", "kills": 0, "score": 0, "players": {"adc": {"id": 18049, "name": "Pl0x", "level": 1, "cs": 0, "assists": 0, "deaths": 0, "kills": 0, "champion": {"id": 3728, "name": "Varus", "slug": "Varus", "image_url": "https://cdn-api.pandascore.co/images/lol/champion/image/b692cde6-0b60-4900-86f3-4f5c36037316.png"}, "summoner_spells": [{"id": 134, "name": "Flash"}, {"id": 129, "name": "Barrier"}]}, "jun": {"id": 7694, "name": "DoubleAiM", "level": 1, "cs": 0, "assists": 0, "deaths": 0, "kills": 0, "champion": {"id": 3666, "name": "Volibear", "slug": "Volibear", "image_url": "https://cdn-api.pandascore.co/images/lol/champion/image/73e72749-ceae-4413-adce-6c1cb863878b.png"}, "summoner_spells": [{"id": 138, "name": "Smite"}, {"id": 134, "name": "Flash"}]}, "mid": {"id": 28790, "name": "Sintax", "level": 1, "cs": 0, "assists": 0, "deaths": 0, "kills": 0, "champion": {"id": 3645, "name": "Taliyah", "slug": "Taliyah", "image_url": "https://cdn-api.pandascore.co/images/lol/champion/image/8fe859d9-af95-4e21-8b1d-9c7c061cd4d2.png"}, "summoner_spells": [{"id": 139, "name": "Teleport"}, {"id": 134, "name": "Flash"}]}, "sup": {"id": 39205, "name": "Lauxio", "level": 1, "cs": 0, "assists": 0, "deaths": 0, "kills": 0, "champion": {"id": 3602, "name": "Nautilus", "slug": "Nautilus", "image_url": "https://cdn-api.pandascore.co/images/lol/champion/image/7f3bc843-2a30-4e14-9cfa-0d8895d2dec4.png"}, "summoner_spells": [{"id": 134, "name": "Flash"}, {"id": 132, "name": "Ignite"}]}, "top": {"id": 37550, "name": "Falleo", "level": 1, "cs": 0, "assists": 0, "deaths": 0, "kills": 0, "champion": {"id": 3703, "name": "Ambessa", "slug": "Ambessa", "image_url": "https://cdn-api.pandascore.co/images/lol/champion/image/4bdc24eb-fcfe-4c11-859e-c76d173aa313.png"}, "summoner_spells": [{"id": 139, "name": "Teleport"}, {"id": 134, "name": "Flash"}]}}, "atakhans": 0, "drakes": 0, "gold": 2500, "heralds": 0, "inhibitors": 0, "nashors": 0, "towers": 0, "voidgrubs": 0, "acronym": "B5"}, "red": {"id": 3340, "name": "Crvena zvezda Esports", "kills": 0, "score": 0, "players": {"adc": {"id": 54354, "name": "Devn", "level": 1, "cs": 0, "assists": 0, "deaths": 0, "kills": 0, "champion": {"id": 3745, "name": "Ezreal", "slug": "Ezreal", "image_url": "https://cdn-api.pandascore.co/images/lol/champion/image/65d28a53-5758-4db1-9d66-d0b68f016ed9.png"}, "summoner_spells": [{"id": 134, "name": "Flash"}, {"id": 129, "name": "Barrier"}]}, "jun": {"id": 32803, "name": "Xeonerr", "level": 1, "cs": 0, "assists": 0, "deaths": 0, "kills": 0, "champion": {"id": 3662, "name": "Vi", "slug": "Vi", "image_url": "https://cdn-api.pandascore.co/images/lol/champion/image/f0e9915e-5f2e-44e9-956d-7b24f4757557.png"}, "summoner_spells": [{"id": 138, "name": "Smite"}, {"id": 134, "name": "Flash"}]}, "mid": {"id": 42195, "name": "Pesho", "level": 1, "cs": 0, "assists": 0, "deaths": 0, "kills": 0, "champion": {"id": 3525, "name": "Aurora", "slug": "Aurora", "image_url": "https://cdn-api.pandascore.co/images/lol/champion/image/fccc9fa8-4ad1-411f-92a0-d43c7b0fc2a0.png"}, "summoner_spells": [{"id": 139, "name": "Teleport"}, {"id": 134, "name": "Flash"}]}, "sup": {"id": 53381, "name": "Zeko", "level": 1, "cs": 0, "assists": 0, "deaths": 0, "kills": 0, "champion": {"id": 3736, "name": "Rell", "slug": "Rell", "image_url": "https://cdn-api.pandascore.co/images/lol/champion/image/04527f37-6ed1-4806-89df-40499a301a24.png"}, "summoner_spells": [{"id": 134, "name": "Flash"}, {"id": 132, "name": "Ignite"}]}, "top": {"id": 52593, "name": "Nenad", "level": 1, "cs": 0, "assists": 0, "deaths": 0, "kills": 0, "champion": {"id": 3630, "name": "Sett", "slug": "Sett", "image_url": "https://cdn-api.pandascore.co/images/lol/champion/image/64d77820-dd57-4ccc-aec1-0492a3e1a74a.png"}, "summoner_spells": [{"id": 139, "name": "Teleport"}, {"id": 134, "name": "Flash"}]}}, "atakhans": 0, "drakes": 0, "gold": 2500, "heralds": 0, "inhibitors": 0, "nashors": 0, "towers": 0, "voidgrubs": 0, "acronym": "CZV"}, "match_id": 1158731, "game_id": 267495, "tournament_id": 16465, "current_timestamp": 0}, {"blue": {"id": 134408, "name": "BeFive", "kills": 0, "score": 0, "players": {"adc": {"id": 18049, "name": "Pl0x", "level": 1, "cs": 0, "assists": 0, "deaths": 0, "kills": 0, "champion": {"id": 3728, "name": "Varus", "slug": "Varus", "image_url": "https://cdn-api.pandascore.co/images/lol/champion/image/b692cde6-0b60-4900-86f3-4f5c36037316.png"}, "summoner_spells": [{"id": 134, "name": "Flash"}, {"id": 129, "name": "Barrier"}]}, "jun": {"id": 7694, "name": "DoubleAiM", "level": 1, "cs": 0, "assists": 0, "deaths": 0, "kills": 0, "champion": {"id": 3666, "name": "Volibear", "slug": "Volibear", "image_url": "https://cdn-api.pandascore.co/images/lol/champion/image/73e72749-ceae-4413-adce-6c1cb863878b.png"}, "summoner_spells": [{"id": 138, "name": "Smite"}, {"id": 134, "name": "Flash"}]}, "mid": {"id": 28790, "name": "Sintax", "level": 1, "cs": 0, "assists": 0, "deaths": 0, "kills": 0, "champion": {"id": 3645, "name": "Taliyah", "slug": "Taliyah", "image_url": "https://cdn-api.pandascore.co/images/lol/champion/image/8fe859d9-af95-4e21-8b1d-9c7c061cd4d2.png"}, "summoner_spells": [{"id": 139, "name": "Teleport"}, {"id": 134, "name": "Flash"}]}, "sup": {"id": 39205, "name": "Lauxio", "level": 1, "cs": 0, "assists": 0, "deaths": 0, "kills": 0, "champion": {"id": 3602, "name": "Nautilus", "slug": "Nautilus", "image_url": "https://cdn-api.pandascore.co/images/lol/champion/image/7f3bc843-2a30-4e14-9cfa-0d8895d2dec4.png"}, "summoner_spells": [{"id": 134, "name": "Flash"}, {"id": 132, "name": "Ignite"}]}, "top": {"id": 37550, "name": "Falleo", "level": 1, "cs": 0, "assists": 0, "deaths": 0, "kills": 0, "champion": {"id": 3703, "name": "Ambessa", "slug": "Ambessa", "image_url": "https://cdn-api.pandascore.co/images/lol/champion/image/4bdc24eb-fcfe-4c11-859e-c76d173aa313.png"}, "summoner_spells": [{"id": 139, "name": "Teleport"}, {"id": 134, "name": "Flash"}]}}, "atakhans": 0, "drakes": 0, "gold": 2500, "heralds": 0, "inhibitors": 0, "nashors": 0, "towers": 0, "voidgrubs": 0, "acronym": "B5"}, "red": {"id": 3340, "name": "Crvena zvezda Esports", "kills": 0, "score": 0, "players": {"adc": {"id": 54354, "name": "Devn", "level": 1, "cs": 0, "assists": 0, "deaths": 0, "kills": 0, "champion": {"id": 3745, "name": "Ezreal", "slug": "Ezreal", "image_url": "https://cdn-api.pandascore.co/images/lol/champion/image/65d28a53-5758-4db1-9d66-d0b68f016ed9.png"}, "summoner_spells": [{"id": 134, "name": "Flash"}, {"id": 129, "name": "Barrier"}]}, "jun": {"id": 32803, "name": "Xeonerr", "level": 1, "cs": 0, "assists": 0, "deaths": 0, "kills": 0, "champion": {"id": 3662, "name": "Vi", "slug": "Vi", "image_url": "https://cdn-api.pandascore.co/images/lol/champion/image/f0e9915e-5f2e-44e9-956d-7b24f4757557.png"}, "summoner_spells": [{"id": 138, "name": "Smite"}, {"id": 134, "name": "Flash"}]}, "mid": {"id": 42195, "name": "Pesho", "level": 1, "cs": 0, "assists": 0, "deaths": 0, "kills": 0, "champion": {"id": 3525, "name": "Aurora", "slug": "Aurora", "image_url": "https://cdn-api.pandascore.co/images/lol/champion/image/fccc9fa8-4ad1-411f-92a0-d43c7b0fc2a0.png"}, "summoner_spells": [{"id": 139, "name": "Teleport"}, {"id": 134, "name": "Flash"}]}, "sup": {"id": 53381, "name": "Zeko", "level": 1, "cs": 0, "assists": 0, "deaths": 0, "kills": 0, "champion": {"id": 3736, "name": "Rell", "slug": "Rell", "image_url": "https://cdn-api.pandascore.co/images/lol/champion/image/04527f37-6ed1-4806-89df-40499a301a24.png"}, "summoner_spells": [{"id": 134, "name": "Flash"}, {"id": 132, "name": "Ignite"}]}, "top": {"id": 52593, "name": "Nenad", "level": 1, "cs": 0, "assists": 0, "deaths": 0, "kills": 0, "champion": {"id": 3630, "name": "Sett", "slug": "Sett", "image_url": "https://cdn-api.pandascore.co/images/lol/champion/image/64d77820-dd57-4ccc-aec1-0492a3e1a74a.png"}, "summoner_spells": [{"id": 139, "name": "Teleport"}, {"id": 134, "name": "Flash"}]}}, "atakhans": 0, "drakes": 0, "gold": 2500, "heralds": 0, "inhibitors": 0, "nashors": 0, "towers": 0, "voidgrubs": 0, "acronym": "CZV"}, "match_id": 1158731, "game_id": 267495, "tournament_id": 16465, "current_timestamp": 60}, {"blue": {"id": 134408, "name": "BeFive", "kills": 0, "score": 0, "players": {"adc": {"id": 18049, "name": "Pl0x", "level": 1, "cs": 3, "assists": 0, "deaths": 0, "kills": 0, "champion": {"id": 3728, "name": "Varus", "slug": "Varus", "image_url": "https://cdn-api.pandascore.co/images/lol/champion/image/b692cde6-0b60-4900-86f3-4f5c36037316.png"}, "summoner_spells": [{"id": 134, "name": "Flash"}, {"id": 129, "name": "Barrier"}]}, "jun": {"id": 7694, "name": "DoubleAiM", "level": 2, "cs": 4, "assists": 0, "deaths": 0, "kills": 0, "champion": {"id": 3666, "name": "Volibear", "slug": "Volibear", "image_url": "https://cdn-api.pandascore.co/images/lol/champion/image/73e72749-ceae-4413-adce-6c1cb863878b.png"}, "summoner_spells": [{"id": 138, "name": "Smite"}, {"id": 134, "name": "Flash"}]}, "mid": {"id": 28790, "name": "Sintax", "level": 1, "cs": 5, "assists": 0, "deaths": 0, "kills": 0, "champion": {"id": 3645, "name": "Taliyah", "slug": "Taliyah", "image_url": "https://cdn-api.pandascore.co/images/lol/champion/image/8fe859d9-af95-4e21-8b1d-9c7c061cd4d2.png"}, "summoner_spells": [{"id": 139, "name": "Teleport"}, {"id": 134, "name": "Flash"}]}, "sup": {"id": 39205, "name": "Lauxio", "level": 1, "cs": 0, "assists": 0, "deaths": 0, "kills": 0, "champion": {"id": 3602, "name": "Nautilus", "slug": "Nautilus", "image_url": "https://cdn-api.pandascore.co/images/lol/champion/image/7f3bc843-2a30-4e14-9cfa-0d8895d2dec4.png"}, "summoner_spells": [{"id": 134, "name": "Flash"}, {"id": 132, "name": "Ignite"}]}, "top": {"id": 37550, "name": "Falleo", "level": 1, "cs": 1, "assists": 0, "deaths": 0, "kills": 0, "champion": {"id": 3703, "name": "Ambessa", "slug": "Ambessa", "image_url": "https://cdn-api.pandascore.co/images/lol/champion/image/4bdc24eb-fcfe-4c11-859e-c76d173aa313.png"}, "summoner_spells": [{"id": 139, "name": "Teleport"}, {"id": 134, "name": "Flash"}]}}, "atakhans": 0, "drakes": 0, "gold": 2969, "heralds": 0, "inhibitors": 0, "nashors": 0, "towers": 0, "voidgrubs": 0, "acronym": "B5"}, "red": {"id": 3340, "name": "Crvena zvezda Esports", "kills": 0, "score": 0, "players": {"adc": {"id": 54354, "name": "Devn", "level": 1, "cs": 6, "assists": 0, "deaths": 0, "kills": 0, "champion": {"id": 3745, "name": "Ezreal", "slug": "Ezreal", "image_url": "https://cdn-api.pandascore.co/images/lol/champion/image/65d28a53-5758-4db1-9d66-d0b68f016ed9.png"}, "summoner_spells": [{"id": 134, "name": "Flash"}, {"id": 129, "name": "Barrier"}]}, "jun": {"id": 32803, "name": "Xeonerr", "level": 2, "cs": 4, "assists": 0, "deaths": 0, "kills": 0, "champion": {"id": 3662, "name": "Vi", "slug": "Vi", "image_url": "https://cdn-api.pandascore.co/images/lol/champion/image/f0e9915e-5f2e-44e9-956d-7b24f4757557.png"}, "summoner_spells": [{"id": 138, "name": "Smite"}, {"id": 134, "name": "Flash"}]}, "mid": {"id": 42195, "name": "Pesho", "level": 1, "cs": 4, "assists": 0, "deaths": 0, "kills": 0, "champion": {"id": 3525, "name": "Aurora", "slug": "Aurora", "image_url": "https://cdn-api.pandascore.co/images/lol/champion/image/fccc9fa8-4ad1-411f-92a0-d43c7b0fc2a0.png"}, "summoner_spells": [{"id": 139, "name": "Teleport"}, {"id": 134, "name": "Flash"}]}, "sup": {"id": 53381, "name": "Zeko", "level": 1, "cs": 1, "assists": 0, "deaths": 0, "kills": 0, "champion": {"id": 3736, "name": "Rell", "slug": "Rell", "image_url": "https://cdn-api.pandascore.co/images/lol/champion/image/04527f37-6ed1-4806-89df-40499a301a24.png"}, "summoner_spells": [{"id": 134, "name": "Flash"}, {"id": 132, "name": "Ignite"}]}, "top": {"id": 52593, "name": "Nenad", "level": 1, "cs": 3, "assists": 0, "deaths": 0, "kills": 0, "champion": {"id": 3630, "name": "Sett", "slug": "Sett", "image_url": "https://cdn-api.pandascore.co/images/lol/champion/image/64d77820-dd57-4ccc-aec1-0492a3e1a74a.png"}, "summoner_spells": [{"id": 139, "name": "Teleport"}, {"id": 134, "name": "Flash"}]}}, "atakhans": 0, "drakes": 0, "gold": 3054, "heralds": 0, "inhibitors": 0, "nashors": 0, "towers": 0, "voidgrubs": 0, "acronym": "CZV"}, "match_id": 1158731, "game_id": 267495, "tournament_id": 16465, "current_timestamp": 120}, {"blue": {"id": 134408, "name": "BeFive", "kills": 0, "score": 0, "players": {"adc": {"id": 18049, "name": "Pl0x", "level": 2, "cs": 16, "assists": 0, "deaths": 0, "kills": 0, "champion": {"id": 3728, "name": "Varus", "slug": "Varus", "image_url": "https://cdn-api.pandascore.co/images/lol/champion/image/b692cde6-0b60-4900-86f3-4f5c36037316.png"}, "summoner_spells": [{"id": 134, "name": "Flash"}, {"id": 129, "name": "Barrier"}]}, "jun": {"id": 7694, "name": "DoubleAiM", "level": 3, "cs": 20, "assists": 0, "deaths": 0, "kills": 0, "champion": {"id": 3666, "name": "Volibear", "slug": "Volibear", "image_url": "https://cdn-api.pandascore.co/images/lol/champion/image/73e72749-ceae-4413-adce-6c1cb863878b.png"}, "summoner_spells": [{"id": 138, "name": "Smite"}, {"id": 134, "name": "Flash"}]}, "mid": {"id": 28790, "name": "Sintax", "level": 3, "cs": 14, "assists": 0, "deaths": 0, "kills": 0, "champion": {"id": 3645, "name": "Taliyah", "slug": "Taliyah", "image_url": "https://cdn-api.pandascore.co/images/lol/champion/image/8fe859d9-af95-4e21-8b1d-9c7c061cd4d2.png"}, "summoner_spells": [{"id": 139, "name": "Teleport"}, {"id": 134, "name": "Flash"}]}, "sup": {"id": 39205, "name": "Lauxio", "level": 2, "cs": 3, "assists": 0, "deaths": 0, "kills": 0, "champion": {"id": 3602, "name": "Nautilus", "slug": "Nautilus", "image_url": "https://cdn-api.pandascore.co/images/lol/champion/image/7f3bc843-2a30-4e14-9cfa-0d8895d2dec4.png"}, "summoner_spells": [{"id": 134, "name": "Flash"}, {"id": 132, "name": "Ignite"}]}, "top": {"id": 37550, "name": "Falleo", "level": 3, "cs": 16, "assists": 0, "deaths": 0, "kills": 0, "champion": {"id": 3703, "name": "Ambessa", "slug": "Ambessa", "image_url": "https://cdn-api.pandascore.co/images/lol/champion/image/4bdc24eb-fcfe-4c11-859e-c76d173aa313.png"}, "summoner_spells": [{"id": 139, "name": "Teleport"}, {"id": 134, "name": "Flash"}]}}, "atakhans": 0, "drakes": 0, "gold": 4634, "heralds": 0, "inhibitors": 0, "nashors": 0, "towers": 0, "voidgrubs": 0, "acronym": "B5"}, "red": {"id": 3340, "name": "Crvena zvezda Esports", "kills": 0, "score": 0, "players": {"adc": {"id": 54354, "name": "Devn", "level": 2, "cs": 14, "assists": 0, "deaths": 0, "kills": 0, "champion": {"id": 3745, "name": "Ezreal", "slug": "Ezreal", "image_url": "https://cdn-api.pandascore.co/images/lol/champion/image/65d28a53-5758-4db1-9d66-d0b68f016ed9.png"}, "summoner_spells": [{"id": 134, "name": "Flash"}, {"id": 129, "name": "Barrier"}]}, "jun": {"id": 32803, "name": "Xeonerr", "level": 3, "cs": 18, "assists": 0, "deaths": 0, "kills": 0, "champion": {"id": 3662, "name": "Vi", "slug": "Vi", "image_url": "https://cdn-api.pandascore.co/images/lol/champion/image/f0e9915e-5f2e-44e9-956d-7b24f4757557.png"}, "summoner_spells": [{"id": 138, "name": "Smite"}, {"id": 134, "name": "Flash"}]}, "mid": {"id": 42195, "name": "Pesho", "level": 3, "cs": 17, "assists": 0, "deaths": 0, "kills": 0, "champion": {"id": 3525, "name": "Aurora", "slug": "Aurora", "image_url": "https://cdn-api.pandascore.co/images/lol/champion/image/fccc9fa8-4ad1-411f-92a0-d43c7b0fc2a0.png"}, "summoner_spells": [{"id": 139, "name": "Teleport"}, {"id": 134, "name": "Flash"}]}, "sup": {"id": 53381, "name": "Zeko", "level": 2, "cs": 2, "assists": 0, "deaths": 0, "kills": 0, "champion": {"id": 3736, "name": "Rell", "slug": "Rell", "image_url": "https://cdn-api.pandascore.co/images/lol/champion/image/04527f37-6ed1-4806-89df-40499a301a24.png"}, "summoner_spells": [{"id": 134, "name": "Flash"}, {"id": 132, "name": "Ignite"}]}, "top": {"id": 52593, "name": "Nenad", "level": 3, "cs": 12, "assists": 0, "deaths": 0, "kills": 0, "champion": {"id": 3630, "name": "Sett", "slug": "Sett", "image_url": "https://cdn-api.pandascore.co/images/lol/champion/image/64d77820-dd57-4ccc-aec1-0492a3e1a74a.png"}, "summoner_spells": [{"id": 139, "name": "Teleport"}, {"id": 134, "name": "Flash"}]}}, "atakhans": 0, "drakes": 0, "gold": 4526, "heralds": 0, "inhibitors": 0, "nashors": 0, "towers": 0, "voidgrubs": 0, "acronym": "CZV"}, "match_id": 1158731, "game_id": 267495, "tournament_id": 16465, "current_timestamp": 180}, {"blue": {"id": 134408, "name": "BeFive", "kills": 0, "score": 0, "players": {"adc": {"id": 18049, "name": "Pl0x", "level": 3, "cs": 29, "assists": 0, "deaths": 1, "kills": 0, "champion": {"id": 3728, "name": "Varus", "slug": "Varus", "image_url": "https://cdn-api.pandascore.co/images/lol/champion/image/b692cde6-0b60-4900-86f3-4f5c36037316.png"}, "summoner_spells": [{"id": 134, "name": "Flash"}, {"id": 129, "name": "Barrier"}]}, "jun": {"id": 7694, "name": "DoubleAiM", "level": 4, "cs": 28, "assists": 0, "deaths": 0, "kills": 0, "champion": {"id": 3666, "name": "Volibear", "slug": "Volibear", "image_url": "https://cdn-api.pandascore.co/images/lol/champion/image/73e72749-ceae-4413-adce-6c1cb863878b.png"}, "summoner_spells": [{"id": 138, "name": "Smite"}, {"id": 134, "name": "Flash"}]}, "mid": {"id": 28790, "name": "Sintax", "level": 4, "cs": 24, "assists": 0, "deaths": 1, "kills": 0, "champion": {"id": 3645, "name": "Taliyah", "slug": "Taliyah", "image_url": "https://cdn-api.pandascore.co/images/lol/champion/image/8fe859d9-af95-4e21-8b1d-9c7c061cd4d2.png"}, "summoner_spells": [{"id": 139, "name": "Teleport"}, {"id": 134, "name": "Flash"}]}, "sup": {"id": 39205, "name": "Lauxio", "level": 3, "cs": 5, "assists": 0, "deaths": 0, "kills": 0, "champion": {"id": 3602, "name": "Nautilus", "slug": "Nautilus", "image_url": "https://cdn-api.pandascore.co/images/lol/champion/image/7f3bc843-2a30-4e14-9cfa-0d8895d2dec4.png"}, "summoner_spells": [{"id": 134, "name": "Flash"}, {"id": 132, "name": "Ignite"}]}, "top": {"id": 37550, "name": "Falleo", "level": 4, "cs": 27, "assists": 0, "deaths": 0, "kills": 0, "champion": {"id": 3703, "name": "Ambessa", "slug": "Ambessa", "image_url": "https://cdn-api.pandascore.co/images/lol/champion/image/4bdc24eb-fcfe-4c11-859e-c76d173aa313.png"}, "summoner_spells": [{"id": 139, "name": "Teleport"}, {"id": 134, "name": "Flash"}]}}, "atakhans": 0, "drakes": 0, "gold": 6212, "heralds": 0, "inhibitors": 0, "nashors": 0, "towers": 0, "voidgrubs": 0, "acronym": "B5"}, "red": {"id": 3340, "name": "Crvena zvezda Esports", "kills": 2, "score": 0, "players": {"adc": {"id": 54354, "name": "Devn", "level": 3, "cs": 23, "assists": 0, "deaths": 0, "kills": 0, "champion": {"id": 3745, "name": "Ezreal", "slug": "Ezreal", "image_url": "https://cdn-api.pandascore.co/images/lol/champion/image/65d28a53-5758-4db1-9d66-d0b68f016ed9.png"}, "summoner_spells": [{"id": 134, "name": "Flash"}, {"id": 129, "name": "Barrier"}]}, "jun": {"id": 32803, "name": "Xeonerr", "level": 4, "cs": 24, "assists": 0, "deaths": 0, "kills": 1, "champion": {"id": 3662, "name": "Vi", "slug": "Vi", "image_url": "https://cdn-api.pandascore.co/images/lol/champion/image/f0e9915e-5f2e-44e9-956d-7b24f4757557.png"}, "summoner_spells": [{"id": 138, "name": "Smite"}, {"id": 134, "name": "Flash"}]}, "mid": {"id": 42195, "name": "Pesho", "level": 4, "cs": 26, "assists": 0, "deaths": 0, "kills": 1, "champion": {"id": 3525, "name": "Aurora", "slug": "Aurora", "image_url": "https://cdn-api.pandascore.co/images/lol/champion/image/fccc9fa8-4ad1-411f-92a0-d43c7b0fc2a0.png"}, "summoner_spells": [{"id": 139, "name": "Teleport"}, {"id": 134, "name": "Flash"}]}, "sup": {"id": 53381, "name": "Zeko", "level": 3, "cs": 4, "assists": 1, "deaths": 0, "kills": 0, "champion": {"id": 3736, "name": "Rell", "slug": "Rell", "image_url": "https://cdn-api.pandascore.co/images/lol/champion/image/04527f37-6ed1-4806-89df-40499a301a24.png"}, "summoner_spells": [{"id": 134, "name": "Flash"}, {"id": 132, "name": "Ignite"}]}, "top": {"id": 52593, "name": "Nenad", "level": 4, "cs": 24, "assists": 0, "deaths": 0, "kills": 0, "champion": {"id": 3630, "name": "Sett", "slug": "Sett", "image_url": "https://cdn-api.pandascore.co/images/lol/champion/image/64d77820-dd57-4ccc-aec1-0492a3e1a74a.png"}, "summoner_spells": [{"id": 139, "name": "Teleport"}, {"id": 134, "name": "Flash"}]}}, "atakhans": 0, "drakes": 0, "gold": 6832, "heralds": 0, "inhibitors": 0, "nashors": 0, "towers": 0, "voidgrubs": 0, "acronym": "CZV"}, "match_id": 1158731, "game_id": 267495, "tournament_id": 16465, "current_timestamp": 240}, {"blue": {"id": 134408, "name": "BeFive", "kills": 0, "score": 0, "players": {"adc": {"id": 18049, "name": "Pl0x", "level": 4, "cs": 34, "assists": 0, "deaths": 1, "kills": 0, "champion": {"id": 3728, "name": "Varus", "slug": "Varus", "image_url": "https://cdn-api.pandascore.co/images/lol/champion/image/b692cde6-0b60-4900-86f3-4f5c36037316.png"}, "summoner_spells": [{"id": 134, "name": "Flash"}, {"id": 129, "name": "Barrier"}]}, "jun": {"id": 7694, "name": "DoubleAiM", "level": 4, "cs": 32, "assists": 0, "deaths": 0, "kills": 0, "champion": {"id": 3666, "name": "Volibear", "slug": "Volibear", "image_url": "https://cdn-api.pandascore.co/images/lol/champion/image/73e72749-ceae-4413-adce-6c1cb863878b.png"}, "summoner_spells": [{"id": 138, "name": "Smite"}, {"id": 134, "name": "Flash"}]}, "mid": {"id": 28790, "name": "Sintax", "level": 5, "cs": 34, "assists": 0, "deaths": 1, "kills": 0, "champion": {"id": 3645, "name": "Taliyah", "slug": "Taliyah", "image_url": "https://cdn-api.pandascore.co/images/lol/champion/image/8fe859d9-af95-4e21-8b1d-9c7c061cd4d2.png"}, "summoner_spells": [{"id": 139, "name": "Teleport"}, {"id": 134, "name": "Flash"}]}, "sup": {"id": 39205, "name": "Lauxio", "level": 4, "cs": 9, "assists": 0, "deaths": 0, "kills": 0, "champion": {"id": 3602, "name": "Nautilus", "slug": "Nautilus", "image_url": "https://cdn-api.pandascore.co/images/lol/champion/image/7f3bc843-2a30-4e14-9cfa-0d8895d2dec4.png"}, "summoner_spells": [{"id": 134, "name": "Flash"}, {"id": 132, "name": "Ignite"}]}, "top": {"id": 37550, "name": "Falleo", "level": 5, "cs": 33, "assists": 0, "deaths": 0, "kills": 0, "champion": {"id": 3703, "name": "Ambessa", "slug": "Ambessa", "image_url": "https://cdn-api.pandascore.co/images/lol/champion/image/4bdc24eb-fcfe-4c11-859e-c76d173aa313.png"}, "summoner_spells": [{"id": 139, "name": "Teleport"}, {"id": 134, "name": "Flash"}]}}, "atakhans": 0, "drakes": 0, "gold": 7446, "heralds": 0, "inhibitors": 0, "nashors": 0, "towers": 0, "voidgrubs": 0, "acronym": "B5"}, "red": {"id": 3340, "name": "Crvena zvezda Esports", "kills": 2, "score": 0, "players": {"adc": {"id": 54354, "name": "Devn", "level": 4, "cs": 32, "assists": 0, "deaths": 0, "kills": 0, "champion": {"id": 3745, "name": "Ezreal", "slug": "Ezreal", "image_url": "https://cdn-api.pandascore.co/images/lol/champion/image/65d28a53-5758-4db1-9d66-d0b68f016ed9.png"}, "summoner_spells": [{"id": 134, "name": "Flash"}, {"id": 129, "name": "Barrier"}]}, "jun": {"id": 32803, "name": "Xeonerr", "level": 4, "cs": 28, "assists": 0, "deaths": 0, "kills": 1, "champion": {"id": 3662, "name": "Vi", "slug": "Vi", "image_url": "https://cdn-api.pandascore.co/images/lol/champion/image/f0e9915e-5f2e-44e9-956d-7b24f4757557.png"}, "summoner_spells": [{"id": 138, "name": "Smite"}, {"id": 134, "name": "Flash"}]}, "mid": {"id": 42195, "name": "Pesho", "level": 5, "cs": 39, "assists": 0, "deaths": 0, "kills": 1, "champion": {"id": 3525, "name": "Aurora", "slug": "Aurora", "image_url": "https://cdn-api.pandascore.co/images/lol/champion/image/fccc9fa8-4ad1-411f-92a0-d43c7b0fc2a0.png"}, "summoner_spells": [{"id": 139, "name": "Teleport"}, {"id": 134, "name": "Flash"}]}, "sup": {"id": 53381, "name": "Zeko", "level": 4, "cs": 6, "assists": 1, "deaths": 0, "kills": 0, "champion": {"id": 3736, "name": "Rell", "slug": "Rell", "image_url": "https://cdn-api.pandascore.co/images/lol/champion/image/04527f37-6ed1-4806-89df-40499a301a24.png"}, "summoner_spells": [{"id": 134, "name": "Flash"}, {"id": 132, "name": "Ignite"}]}, "top": {"id": 52593, "name": "Nenad", "level": 5, "cs": 33, "assists": 0, "deaths": 0, "kills": 0, "champion": {"id": 3630, "name": "Sett", "slug": "Sett", "image_url": "https://cdn-api.pandascore.co/images/lol/champion/image/64d77820-dd57-4ccc-aec1-0492a3e1a74a.png"}, "summoner_spells": [{"id": 139, "name": "Teleport"}, {"id": 134, "name": "Flash"}]}}, "atakhans": 0, "drakes": 0, "gold": 8280, "heralds": 0, "inhibitors": 0, "nashors": 0, "towers": 0, "voidgrubs": 0, "acronym": "CZV"}, "match_id": 1158731, "game_id": 267495, "tournament_id": 16465, "current_timestamp": 300}, {"blue": {"id": 134408, "name": "BeFive", "kills": 1, "score": 0, "players": {"adc": {"id": 18049, "name": "Pl0x", "level": 4, "cs": 46, "assists": 0, "deaths": 1, "kills": 0, "champion": {"id": 3728, "name": "Varus", "slug": "Varus", "image_url": "https://cdn-api.pandascore.co/images/lol/champion/image/b692cde6-0b60-4900-86f3-4f5c36037316.png"}, "summoner_spells": [{"id": 134, "name": "Flash"}, {"id": 129, "name": "Barrier"}]}, "jun": {"id": 7694, "name": "DoubleAiM", "level": 5, "cs": 36, "assists": 0, "deaths": 0, "kills": 1, "champion": {"id": 3666, "name": "Volibear", "slug": "Volibear", "image_url": "https://cdn-api.pandascore.co/images/lol/champion/image/73e72749-ceae-4413-adce-6c1cb863878b.png"}, "summoner_spells": [{"id": 138, "name": "Smite"}, {"id": 134, "name": "Flash"}]}, "mid": {"id": 28790, "name": "Sintax", "level": 6, "cs": 39, "assists": 1, "deaths": 2, "kills": 0, "champion": {"id": 3645, "name": "Taliyah", "slug": "Taliyah", "image_url": "https://cdn-api.pandascore.co/images/lol/champion/image/8fe859d9-af95-4e21-8b1d-9c7c061cd4d2.png"}, "summoner_spells": [{"id": 139, "name": "Teleport"}, {"id": 134, "name": "Flash"}]}, "sup": {"id": 39205, "name": "Lauxio", "level": 4, "cs": 10, "assists": 0, "deaths": 0, "kills": 0, "champion": {"id": 3602, "name": "Nautilus", "slug": "Nautilus", "image_url": "https://cdn-api.pandascore.co/images/lol/champion/image/7f3bc843-2a30-4e14-9cfa-0d8895d2dec4.png"}, "summoner_spells": [{"id": 134, "name": "Flash"}, {"id": 132, "name": "Ignite"}]}, "top": {"id": 37550, "name": "Falleo", "level": 6, "cs": 47, "assists": 0, "deaths": 0, "kills": 0, "champion": {"id": 3703, "name": "Ambessa", "slug": "Ambessa", "image_url": "https://cdn-api.pandascore.co/images/lol/champion/image/4bdc24eb-fcfe-4c11-859e-c76d173aa313.png"}, "summoner_spells": [{"id": 139, "name": "Teleport"}, {"id": 134, "name": "Flash"}]}}, "atakhans": 0, "drakes": 0, "gold": 9333, "heralds": 0, "inhibitors": 0, "nashors": 0, "towers": 0, "voidgrubs": 0, "acronym": "B5"}, "red": {"id": 3340, "name": "Crvena zvezda Esports", "kills": 3, "score": 0, "players": {"adc": {"id": 54354, "name": "Devn", "level": 5, "cs": 46, "assists": 0, "deaths": 0, "kills": 0, "champion": {"id": 3745, "name": "Ezreal", "slug": "Ezreal", "image_url": "https://cdn-api.pandascore.co/images/lol/champion/image/65d28a53-5758-4db1-9d66-d0b68f016ed9.png"}, "summoner_spells": [{"id": 134, "name": "Flash"}, {"id": 129, "name": "Barrier"}]}, "jun": {"id": 32803, "name": "Xeonerr", "level": 5, "cs": 40, "assists": 0, "deaths": 0, "kills": 1, "champion": {"id": 3662, "name": "Vi", "slug": "Vi", "image_url": "https://cdn-api.pandascore.co/images/lol/champion/image/f0e9915e-5f2e-44e9-956d-7b24f4757557.png"}, "summoner_spells": [{"id": 138, "name": "Smite"}, {"id": 134, "name": "Flash"}]}, "mid": {"id": 42195, "name": "Pesho", "level": 6, "cs": 50, "assists": 0, "deaths": 1, "kills": 2, "champion": {"id": 3525, "name": "Aurora", "slug": "Aurora", "image_url": "https://cdn-api.pandascore.co/images/lol/champion/image/fccc9fa8-4ad1-411f-92a0-d43c7b0fc2a0.png"}, "summoner_spells": [{"id": 139, "name": "Teleport"}, {"id": 134, "name": "Flash"}]}, "sup": {"id": 53381, "name": "Zeko", "level": 4, "cs": 9, "assists": 1, "deaths": 0, "kills": 0, "champion": {"id": 3736, "name": "Rell", "slug": "Rell", "image_url": "https://cdn-api.pandascore.co/images/lol/champion/image/04527f37-6ed1-4806-89df-40499a301a24.png"}, "summoner_spells": [{"id": 134, "name": "Flash"}, {"id": 132, "name": "Ignite"}]}, "top": {"id": 52593, "name": "Nenad", "level": 6, "cs": 43, "assists": 0, "deaths": 0, "kills": 0, "champion": {"id": 3630, "name": "Sett", "slug": "Sett", "image_url": "https://cdn-api.pandascore.co/images/lol/champion/image/64d77820-dd57-4ccc-aec1-0492a3e1a74a.png"}, "summoner_spells": [{"id": 139, "name": "Teleport"}, {"id": 134, "name": "Flash"}]}}, "atakhans": 0, "drakes": 0, "gold": 10210, "heralds": 0, "inhibitors": 0, "nashors": 0, "towers": 0, "voidgrubs": 0, "acronym": "CZV"}, "match_id": 1158731, "game_id": 267495, "tournament_id": 16465, "current_timestamp": 360}, {"blue": {"id": 134408, "name": "BeFive", "kills": 1, "score": 0, "players": {"adc": {"id": 18049, "name": "Pl0x", "level": 5, "cs": 58, "assists": 0, "deaths": 1, "kills": 0, "champion": {"id": 3728, "name": "Varus", "slug": "Varus", "image_url": "https://cdn-api.pandascore.co/images/lol/champion/image/b692cde6-0b60-4900-86f3-4f5c36037316.png"}, "summoner_spells": [{"id": 134, "name": "Flash"}, {"id": 129, "name": "Barrier"}]}, "jun": {"id": 7694, "name": "DoubleAiM", "level": 5, "cs": 46, "assists": 0, "deaths": 0, "kills": 1, "champion": {"id": 3666, "name": "Volibear", "slug": "Volibear", "image_url": "https://cdn-api.pandascore.co/images/lol/champion/image/73e72749-ceae-4413-adce-6c1cb863878b.png"}, "summoner_spells": [{"id": 138, "name": "Smite"}, {"id": 134, "name": "Flash"}]}, "mid": {"id": 28790, "name": "Sintax", "level": 6, "cs": 50, "assists": 1, "deaths": 2, "kills": 0, "champion": {"id": 3645, "name": "Taliyah", "slug": "Taliyah", "image_url": "https://cdn-api.pandascore.co/images/lol/champion/image/8fe859d9-af95-4e21-8b1d-9c7c061cd4d2.png"}, "summoner_spells": [{"id": 139, "name": "Teleport"}, {"id": 134, "name": "Flash"}]}, "sup": {"id": 39205, "name": "Lauxio", "level": 5, "cs": 13, "assists": 0, "deaths": 0, "kills": 0, "champion": {"id": 3602, "name": "Nautilus", "slug": "Nautilus", "image_url": "https://cdn-api.pandascore.co/images/lol/champion/image/7f3bc843-2a30-4e14-9cfa-0d8895d2dec4.png"}, "summoner_spells": [{"id": 134, "name": "Flash"}, {"id": 132, "name": "Ignite"}]}, "top": {"id": 37550, "name": "Falleo", "level": 7, "cs": 57, "assists": 0, "deaths": 0, "kills": 0, "champion": {"id": 3703, "name": "Ambessa", "slug": "Ambessa", "image_url": "https://cdn-api.pandascore.co/images/lol/champion/image/4bdc24eb-fcfe-4c11-859e-c76d173aa313.png"}, "summoner_spells": [{"id": 139, "name": "Teleport"}, {"id": 134, "name": "Flash"}]}}, "atakhans": 0, "drakes": 0, "gold": 11081, "heralds": 0, "inhibitors": 0, "nashors": 0, "towers": 0, "voidgrubs": 3, "acronym": "B5"}, "red": {"id": 3340, "name": "Crvena zvezda Esports", "kills": 3, "score": 0, "players": {"adc": {"id": 54354, "name": "Devn", "level": 5, "cs": 54, "assists": 0, "deaths": 0, "kills": 0, "champion": {"id": 3745, "name": "Ezreal", "slug": "Ezreal", "image_url": "https://cdn-api.pandascore.co/images/lol/champion/image/65d28a53-5758-4db1-9d66-d0b68f016ed9.png"}, "summoner_spells": [{"id": 134, "name": "Flash"}, {"id": 129, "name": "Barrier"}]}, "jun": {"id": 32803, "name": "Xeonerr", "level": 5, "cs": 44, "assists": 0, "deaths": 0, "kills": 1, "champion": {"id": 3662, "name": "Vi", "slug": "Vi", "image_url": "https://cdn-api.pandascore.co/images/lol/champion/image/f0e9915e-5f2e-44e9-956d-7b24f4757557.png"}, "summoner_spells": [{"id": 138, "name": "Smite"}, {"id": 134, "name": "Flash"}]}, "mid": {"id": 42195, "name": "Pesho", "level": 7, "cs": 59, "assists": 0, "deaths": 1, "kills": 2, "champion": {"id": 3525, "name": "Aurora", "slug": "Aurora", "image_url": "https://cdn-api.pandascore.co/images/lol/champion/image/fccc9fa8-4ad1-411f-92a0-d43c7b0fc2a0.png"}, "summoner_spells": [{"id": 139, "name": "Teleport"}, {"id": 134, "name": "Flash"}]}, "sup": {"id": 53381, "name": "Zeko", "level": 5, "cs": 10, "assists": 1, "deaths": 0, "kills": 0, "champion": {"id": 3736, "name": "Rell", "slug": "Rell", "image_url": "https://cdn-api.pandascore.co/images/lol/champion/image/04527f37-6ed1-4806-89df-40499a301a24.png"}, "summoner_spells": [{"id": 134, "name": "Flash"}, {"id": 132, "name": "Ignite"}]}, "top": {"id": 52593, "name": "Nenad", "level": 7, "cs": 52, "assists": 0, "deaths": 0, "kills": 0, "champion": {"id": 3630, "name": "Sett", "slug": "Sett", "image_url": "https://cdn-api.pandascore.co/images/lol/champion/image/64d77820-dd57-4ccc-aec1-0492a3e1a74a.png"}, "summoner_spells": [{"id": 139, "name": "Teleport"}, {"id": 134, "name": "Flash"}]}}, "atakhans": 0, "drakes": 1, "gold": 11486, "heralds": 0, "inhibitors": 0, "nashors": 0, "towers": 0, "voidgrubs": 0, "acronym": "CZV"}, "match_id": 1158731, "game_id": 267495, "tournament_id": 16465, "current_timestamp": 420}, {"blue": {"id": 134408, "name": "BeFive", "kills": 2, "score": 0, "players": {"adc": {"id": 18049, "name": "Pl0x", "level": 5, "cs": 60, "assists": 0, "deaths": 1, "kills": 0, "champion": {"id": 3728, "name": "Varus", "slug": "Varus", "image_url": "https://cdn-api.pandascore.co/images/lol/champion/image/b692cde6-0b60-4900-86f3-4f5c36037316.png"}, "summoner_spells": [{"id": 134, "name": "Flash"}, {"id": 129, "name": "Barrier"}]}, "jun": {"id": 7694, "name": "DoubleAiM", "level": 6, "cs": 54, "assists": 1, "deaths": 0, "kills": 1, "champion": {"id": 3666, "name": "Volibear", "slug": "Volibear", "image_url": "https://cdn-api.pandascore.co/images/lol/champion/image/73e72749-ceae-4413-adce-6c1cb863878b.png"}, "summoner_spells": [{"id": 138, "name": "Smite"}, {"id": 134, "name": "Flash"}]}, "mid": {"id": 28790, "name": "Sintax", "level": 7, "cs": 58, "assists": 2, "deaths": 2, "kills": 0, "champion": {"id": 3645, "name": "Taliyah", "slug": "Taliyah", "image_url": "https://cdn-api.pandascore.co/images/lol/champion/image/8fe859d9-af95-4e21-8b1d-9c7c061cd4d2.png"}, "summoner_spells": [{"id": 139, "name": "Teleport"}, {"id": 134, "name": "Flash"}]}, "sup": {"id": 39205, "name": "Lauxio", "level": 5, "cs": 13, "assists": 0, "deaths": 0, "kills": 0, "champion": {"id": 3602, "name": "Nautilus", "slug": "Nautilus", "image_url": "https://cdn-api.pandascore.co/images/lol/champion/image/7f3bc843-2a30-4e14-9cfa-0d8895d2dec4.png"}, "summoner_spells": [{"id": 134, "name": "Flash"}, {"id": 132, "name": "Ignite"}]}, "top": {"id": 37550, "name": "Falleo", "level": 7, "cs": 62, "assists": 0, "deaths": 1, "kills": 1, "champion": {"id": 3703, "name": "Ambessa", "slug": "Ambessa", "image_url": "https://cdn-api.pandascore.co/images/lol/champion/image/4bdc24eb-fcfe-4c11-859e-c76d173aa313.png"}, "summoner_spells": [{"id": 139, "name": "Teleport"}, {"id": 134, "name": "Flash"}]}}, "atakhans": 0, "drakes": 0, "gold": 12871, "heralds": 0, "inhibitors": 0, "nashors": 0, "towers": 0, "voidgrubs": 3, "acronym": "B5"}, "red": {"id": 3340, "name": "Crvena zvezda Esports", "kills": 4, "score": 0, "players": {"adc": {"id": 54354, "name": "Devn", "level": 6, "cs": 70, "assists": 1, "deaths": 0, "kills": 0, "champion": {"id": 3745, "name": "Ezreal", "slug": "Ezreal", "image_url": "https://cdn-api.pandascore.co/images/lol/champion/image/65d28a53-5758-4db1-9d66-d0b68f016ed9.png"}, "summoner_spells": [{"id": 134, "name": "Flash"}, {"id": 129, "name": "Barrier"}]}, "jun": {"id": 32803, "name": "Xeonerr", "level": 6, "cs": 56, "assists": 0, "deaths": 0, "kills": 1, "champion": {"id": 3662, "name": "Vi", "slug": "Vi", "image_url": "https://cdn-api.pandascore.co/images/lol/champion/image/f0e9915e-5f2e-44e9-956d-7b24f4757557.png"}, "summoner_spells": [{"id": 138, "name": "Smite"}, {"id": 134, "name": "Flash"}]}, "mid": {"id": 42195, "name": "Pesho", "level": 8, "cs": 75, "assists": 0, "deaths": 1, "kills": 2, "champion": {"id": 3525, "name": "Aurora", "slug": "Aurora", "image_url": "https://cdn-api.pandascore.co/images/lol/champion/image/fccc9fa8-4ad1-411f-92a0-d43c7b0fc2a0.png"}, "summoner_spells": [{"id": 139, "name": "Teleport"}, {"id": 134, "name": "Flash"}]}, "sup": {"id": 53381, "name": "Zeko", "level": 5, "cs": 10, "assists": 1, "deaths": 0, "kills": 0, "champion": {"id": 3736, "name": "Rell", "slug": "Rell", "image_url": "https://cdn-api.pandascore.co/images/lol/champion/image/04527f37-6ed1-4806-89df-40499a301a24.png"}, "summoner_spells": [{"id": 134, "name": "Flash"}, {"id": 132, "name": "Ignite"}]}, "top": {"id": 52593, "name": "Nenad", "level": 7, "cs": 58, "assists": 0, "deaths": 1, "kills": 1, "champion": {"id": 3630, "name": "Sett", "slug": "Sett", "image_url": "https://cdn-api.pandascore.co/images/lol/champion/image/64d77820-dd57-4ccc-aec1-0492a3e1a74a.png"}, "summoner_spells": [{"id": 139, "name": "Teleport"}, {"id": 134, "name": "Flash"}]}}, "atakhans": 0, "drakes": 1, "gold": 13867, "heralds": 0, "inhibitors": 0, "nashors": 0, "towers": 0, "voidgrubs": 0, "acronym": "CZV"}, "match_id": 1158731, "game_id": 267495, "tournament_id": 16465, "current_timestamp": 480}, {"blue": {"id": 134408, "name": "BeFive", "kills": 2, "score": 0, "players": {"adc": {"id": 18049, "name": "Pl0x", "level": 6, "cs": 76, "assists": 0, "deaths": 1, "kills": 0, "champion": {"id": 3728, "name": "Varus", "slug": "Varus", "image_url": "https://cdn-api.pandascore.co/images/lol/champion/image/b692cde6-0b60-4900-86f3-4f5c36037316.png"}, "summoner_spells": [{"id": 134, "name": "Flash"}, {"id": 129, "name": "Barrier"}]}, "jun": {"id": 7694, "name": "DoubleAiM", "level": 7, "cs": 63, "assists": 1, "deaths": 0, "kills": 1, "champion": {"id": 3666, "name": "Volibear", "slug": "Volibear", "image_url": "https://cdn-api.pandascore.co/images/lol/champion/image/73e72749-ceae-4413-adce-6c1cb863878b.png"}, "summoner_spells": [{"id": 138, "name": "Smite"}, {"id": 134, "name": "Flash"}]}, "mid": {"id": 28790, "name": "Sintax", "level": 7, "cs": 66, "assists": 2, "deaths": 2, "kills": 0, "champion": {"id": 3645, "name": "Taliyah", "slug": "Taliyah", "image_url": "https://cdn-api.pandascore.co/images/lol/champion/image/8fe859d9-af95-4e21-8b1d-9c7c061cd4d2.png"}, "summoner_spells": [{"id": 139, "name": "Teleport"}, {"id": 134, "name": "Flash"}]}, "sup": {"id": 39205, "name": "Lauxio", "level": 5, "cs": 16, "assists": 0, "deaths": 0, "kills": 0, "champion": {"id": 3602, "name": "Nautilus", "slug": "Nautilus", "image_url": "https://cdn-api.pandascore.co/images/lol/champion/image/7f3bc843-2a30-4e14-9cfa-0d8895d2dec4.png"}, "summoner_spells": [{"id": 134, "name": "Flash"}, {"id": 132, "name": "Ignite"}]}, "top": {"id": 37550, "name": "Falleo", "level": 7, "cs": 66, "assists": 0, "deaths": 1, "kills": 1, "champion": {"id": 3703, "name": "Ambessa", "slug": "Ambessa", "image_url": "https://cdn-api.pandascore.co/images/lol/champion/image/4bdc24eb-fcfe-4c11-859e-c76d173aa313.png"}, "summoner_spells": [{"id": 139, "name": "Teleport"}, {"id": 134, "name": "Flash"}]}}, "atakhans": 0, "drakes": 0, "gold": 14377, "heralds": 0, "inhibitors": 0, "nashors": 0, "towers": 0, "voidgrubs": 3, "acronym": "B5"}, "red": {"id": 3340, "name": "Crvena zvezda Esports", "kills": 4, "score": 0, "players": {"adc": {"id": 54354, "name": "Devn", "level": 7, "cs": 80, "assists": 1, "deaths": 0, "kills": 0, "champion": {"id": 3745, "name": "Ezreal", "slug": "Ezreal", "image_url": "https://cdn-api.pandascore.co/images/lol/champion/image/65d28a53-5758-4db1-9d66-d0b68f016ed9.png"}, "summoner_spells": [{"id": 134, "name": "Flash"}, {"id": 129, "name": "Barrier"}]}, "jun": {"id": 32803, "name": "Xeonerr", "level": 7, "cs": 62, "assists": 0, "deaths": 0, "kills": 1, "champion": {"id": 3662, "name": "Vi", "slug": "Vi", "image_url": "https://cdn-api.pandascore.co/images/lol/champion/image/f0e9915e-5f2e-44e9-956d-7b24f4757557.png"}, "summoner_spells": [{"id": 138, "name": "Smite"}, {"id": 134, "name": "Flash"}]}, "mid": {"id": 42195, "name": "Pesho", "level": 8, "cs": 81, "assists": 0, "deaths": 1, "kills": 2, "champion": {"id": 3525, "name": "Aurora", "slug": "Aurora", "image_url": "https://cdn-api.pandascore.co/images/lol/champion/image/fccc9fa8-4ad1-411f-92a0-d43c7b0fc2a0.png"}, "summoner_spells": [{"id": 139, "name": "Teleport"}, {"id": 134, "name": "Flash"}]}, "sup": {"id": 53381, "name": "Zeko", "level": 5, "cs": 14, "assists": 1, "deaths": 0, "kills": 0, "champion": {"id": 3736, "name": "Rell", "slug": "Rell", "image_url": "https://cdn-api.pandascore.co/images/lol/champion/image/04527f37-6ed1-4806-89df-40499a301a24.png"}, "summoner_spells": [{"id": 134, "name": "Flash"}, {"id": 132, "name": "Ignite"}]}, "top": {"id": 52593, "name": "Nenad", "level": 8, "cs": 69, "assists": 0, "deaths": 1, "kills": 1, "champion": {"id": 3630, "name": "Sett", "slug": "Sett", "image_url": "https://cdn-api.pandascore.co/images/lol/champion/image/64d77820-dd57-4ccc-aec1-0492a3e1a74a.png"}, "summoner_spells": [{"id": 139, "name": "Teleport"}, {"id": 134, "name": "Flash"}]}}, "atakhans": 0, "drakes": 1, "gold": 15319, "heralds": 0, "inhibitors": 0, "nashors": 0, "towers": 0, "voidgrubs": 0, "acronym": "CZV"}, "match_id": 1158731, "game_id": 267495, "tournament_id": 16465, "current_timestamp": 540}, {"blue": {"id": 134408, "name": "BeFive", "kills": 2, "score": 0, "players": {"adc": {"id": 18049, "name": "Pl0x", "level": 6, "cs": 83, "assists": 0, "deaths": 1, "kills": 0, "champion": {"id": 3728, "name": "Varus", "slug": "Varus", "image_url": "https://cdn-api.pandascore.co/images/lol/champion/image/b692cde6-0b60-4900-86f3-4f5c36037316.png"}, "summoner_spells": [{"id": 134, "name": "Flash"}, {"id": 129, "name": "Barrier"}]}, "jun": {"id": 7694, "name": "DoubleAiM", "level": 7, "cs": 71, "assists": 1, "deaths": 1, "kills": 1, "champion": {"id": 3666, "name": "Volibear", "slug": "Volibear", "image_url": "https://cdn-api.pandascore.co/images/lol/champion/image/73e72749-ceae-4413-adce-6c1cb863878b.png"}, "summoner_spells": [{"id": 138, "name": "Smite"}, {"id": 134, "name": "Flash"}]}, "mid": {"id": 28790, "name": "Sintax", "level": 8, "cs": 71, "assists": 2, "deaths": 3, "kills": 0, "champion": {"id": 3645, "name": "Taliyah", "slug": "Taliyah", "image_url": "https://cdn-api.pandascore.co/images/lol/champion/image/8fe859d9-af95-4e21-8b1d-9c7c061cd4d2.png"}, "summoner_spells": [{"id": 139, "name": "Teleport"}, {"id": 134, "name": "Flash"}]}, "sup": {"id": 39205, "name": "Lauxio", "level": 6, "cs": 18, "assists": 0, "deaths": 0, "kills": 0, "champion": {"id": 3602, "name": "Nautilus", "slug": "Nautilus", "image_url": "https://cdn-api.pandascore.co/images/lol/champion/image/7f3bc843-2a30-4e14-9cfa-0d8895d2dec4.png"}, "summoner_spells": [{"id": 134, "name": "Flash"}, {"id": 132, "name": "Ignite"}]}, "top": {"id": 37550, "name": "Falleo", "level": 8, "cs": 69, "assists": 0, "deaths": 2, "kills": 1, "champion": {"id": 3703, "name": "Ambessa", "slug": "Ambessa", "image_url": "https://cdn-api.pandascore.co/images/lol/champion/image/4bdc24eb-fcfe-4c11-859e-c76d173aa313.png"}, "summoner_spells": [{"id": 139, "name": "Teleport"}, {"id": 134, "name": "Flash"}]}}, "atakhans": 0, "drakes": 0, "gold": 15790, "heralds": 0, "inhibitors": 0, "nashors": 0, "towers": 0, "voidgrubs": 3, "acronym": "B5"}, "red": {"id": 3340, "name": "Crvena zvezda Esports", "kills": 7, "score": 0, "players": {"adc": {"id": 54354, "name": "Devn", "level": 7, "cs": 88, "assists": 1, "deaths": 0, "kills": 0, "champion": {"id": 3745, "name": "Ezreal", "slug": "Ezreal", "image_url": "https://cdn-api.pandascore.co/images/lol/champion/image/65d28a53-5758-4db1-9d66-d0b68f016ed9.png"}, "summoner_spells": [{"id": 134, "name": "Flash"}, {"id": 129, "name": "Barrier"}]}, "jun": {"id": 32803, "name": "Xeonerr", "level": 7, "cs": 66, "assists": 3, "deaths": 0, "kills": 1, "champion": {"id": 3662, "name": "Vi", "slug": "Vi", "image_url": "https://cdn-api.pandascore.co/images/lol/champion/image/f0e9915e-5f2e-44e9-956d-7b24f4757557.png"}, "summoner_spells": [{"id": 138, "name": "Smite"}, {"id": 134, "name": "Flash"}]}, "mid": {"id": 42195, "name": "Pesho", "level": 9, "cs": 90, "assists": 0, "deaths": 1, "kills": 4, "champion": {"id": 3525, "name": "Aurora", "slug": "Aurora", "image_url": "https://cdn-api.pandascore.co/images/lol/champion/image/fccc9fa8-4ad1-411f-92a0-d43c7b0fc2a0.png"}, "summoner_spells": [{"id": 139, "name": "Teleport"}, {"id": 134, "name": "Flash"}]}, "sup": {"id": 53381, "name": "Zeko", "level": 6, "cs": 18, "assists": 1, "deaths": 0, "kills": 0, "champion": {"id": 3736, "name": "Rell", "slug": "Rell", "image_url": "https://cdn-api.pandascore.co/images/lol/champion/image/04527f37-6ed1-4806-89df-40499a301a24.png"}, "summoner_spells": [{"id": 134, "name": "Flash"}, {"id": 132, "name": "Ignite"}]}, "top": {"id": 52593, "name": "Nenad", "level": 8, "cs": 76, "assists": 0, "deaths": 1, "kills": 2, "champion": {"id": 3630, "name": "Sett", "slug": "Sett", "image_url": "https://cdn-api.pandascore.co/images/lol/champion/image/64d77820-dd57-4ccc-aec1-0492a3e1a74a.png"}, "summoner_spells": [{"id": 139, "name": "Teleport"}, {"id": 134, "name": "Flash"}]}}, "atakhans": 0, "drakes": 1, "gold": 18091, "heralds": 0, "inhibitors": 0, "nashors": 0, "towers": 0, "voidgrubs": 0, "acronym": "CZV"}, "match_id": 1158731, "game_id": 267495, "tournament_id": 16465, "current_timestamp": 600}, {"blue": {"id": 134408, "name": "BeFive", "kills": 4, "score": 0, "players": {"adc": {"id": 18049, "name": "Pl0x", "level": 7, "cs": 97, "assists": 1, "deaths": 1, "kills": 1, "champion": {"id": 3728, "name": "Varus", "slug": "Varus", "image_url": "https://cdn-api.pandascore.co/images/lol/champion/image/b692cde6-0b60-4900-86f3-4f5c36037316.png"}, "summoner_spells": [{"id": 134, "name": "Flash"}, {"id": 129, "name": "Barrier"}]}, "jun": {"id": 7694, "name": "DoubleAiM", "level": 7, "cs": 72, "assists": 1, "deaths": 1, "kills": 1, "champion": {"id": 3666, "name": "Volibear", "slug": "Volibear", "image_url": "https://cdn-api.pandascore.co/images/lol/champion/image/73e72749-ceae-4413-adce-6c1cb863878b.png"}, "summoner_spells": [{"id": 138, "name": "Smite"}, {"id": 134, "name": "Flash"}]}, "mid": {"id": 28790, "name": "Sintax", "level": 8, "cs": 78, "assists": 3, "deaths": 3, "kills": 1, "champion": {"id": 3645, "name": "Taliyah", "slug": "Taliyah", "image_url": "https://cdn-api.pandascore.co/images/lol/champion/image/8fe859d9-af95-4e21-8b1d-9c7c061cd4d2.png"}, "summoner_spells": [{"id": 139, "name": "Teleport"}, {"id": 134, "name": "Flash"}]}, "sup": {"id": 39205, "name": "Lauxio", "level": 7, "cs": 23, "assists": 2, "deaths": 0, "kills": 0, "champion": {"id": 3602, "name": "Nautilus", "slug": "Nautilus", "image_url": "https://cdn-api.pandascore.co/images/lol/champion/image/7f3bc843-2a30-4e14-9cfa-0d8895d2dec4.png"}, "summoner_spells": [{"id": 134, "name": "Flash"}, {"id": 132, "name": "Ignite"}]}, "top": {"id": 37550, "name": "Falleo", "level": 8, "cs": 79, "assists": 0, "deaths": 2, "kills": 1, "champion": {"id": 3703, "name": "Ambessa", "slug": "Ambessa", "image_url": "https://cdn-api.pandascore.co/images/lol/champion/image/4bdc24eb-fcfe-4c11-859e-c76d173aa313.png"}, "summoner_spells": [{"id": 139, "name": "Teleport"}, {"id": 134, "name": "Flash"}]}}, "atakhans": 0, "drakes": 0, "gold": 18267, "heralds": 0, "inhibitors": 0, "nashors": 0, "towers": 0, "voidgrubs": 3, "acronym": "B5"}, "red": {"id": 3340, "name": "Crvena zvezda Esports", "kills": 7, "score": 0, "players": {"adc": {"id": 54354, "name": "Devn", "level": 7, "cs": 96, "assists": 1, "deaths": 0, "kills": 0, "champion": {"id": 3745, "name": "Ezreal", "slug": "Ezreal", "image_url": "https://cdn-api.pandascore.co/images/lol/champion/image/65d28a53-5758-4db1-9d66-d0b68f016ed9.png"}, "summoner_spells": [{"id": 134, "name": "Flash"}, {"id": 129, "name": "Barrier"}]}, "jun": {"id": 32803, "name": "Xeonerr", "level": 8, "cs": 76, "assists": 3, "deaths": 0, "kills": 1, "champion": {"id": 3662, "name": "Vi", "slug": "Vi", "image_url": "https://cdn-api.pandascore.co/images/lol/champion/image/f0e9915e-5f2e-44e9-956d-7b24f4757557.png"}, "summoner_spells": [{"id": 138, "name": "Smite"}, {"id": 134, "name": "Flash"}]}, "mid": {"id": 42195, "name": "Pesho", "level": 9, "cs": 99, "assists": 0, "deaths": 2, "kills": 4, "champion": {"id": 3525, "name": "Aurora", "slug": "Aurora", "image_url": "https://cdn-api.pandascore.co/images/lol/champion/image/fccc9fa8-4ad1-411f-92a0-d43c7b0fc2a0.png"}, "summoner_spells": [{"id": 139, "name": "Teleport"}, {"id": 134, "name": "Flash"}]}, "sup": {"id": 53381, "name": "Zeko", "level": 6, "cs": 18, "assists": 1, "deaths": 1, "kills": 0, "champion": {"id": 3736, "name": "Rell", "slug": "Rell", "image_url": "https://cdn-api.pandascore.co/images/lol/champion/image/04527f37-6ed1-4806-89df-40499a301a24.png"}, "summoner_spells": [{"id": 134, "name": "Flash"}, {"id": 132, "name": "Ignite"}]}, "top": {"id": 52593, "name": "Nenad", "level": 9, "cs": 87, "assists": 0, "deaths": 1, "kills": 2, "champion": {"id": 3630, "name": "Sett", "slug": "Sett", "image_url": "https://cdn-api.pandascore.co/images/lol/champion/image/64d77820-dd57-4ccc-aec1-0492a3e1a74a.png"}, "summoner_spells": [{"id": 139, "name": "Teleport"}, {"id": 134, "name": "Flash"}]}}, "atakhans": 0, "drakes": 1, "gold": 19691, "heralds": 0, "inhibitors": 0, "nashors": 0, "towers": 0, "voidgrubs": 1, "acronym": "CZV"}, "match_id": 1158731, "game_id": 267495, "tournament_id": 16465, "current_timestamp": 660}, {"blue": {"id": 134408, "name": "BeFive", "kills": 4, "score": 0, "players": {"adc": {"id": 18049, "name": "Pl0x", "level": 8, "cs": 110, "assists": 1, "deaths": 1, "kills": 1, "champion": {"id": 3728, "name": "Varus", "slug": "Varus", "image_url": "https://cdn-api.pandascore.co/images/lol/champion/image/b692cde6-0b60-4900-86f3-4f5c36037316.png"}, "summoner_spells": [{"id": 134, "name": "Flash"}, {"id": 129, "name": "Barrier"}]}, "jun": {"id": 7694, "name": "DoubleAiM", "level": 8, "cs": 84, "assists": 1, "deaths": 1, "kills": 1, "champion": {"id": 3666, "name": "Volibear", "slug": "Volibear", "image_url": "https://cdn-api.pandascore.co/images/lol/champion/image/73e72749-ceae-4413-adce-6c1cb863878b.png"}, "summoner_spells": [{"id": 138, "name": "Smite"}, {"id": 134, "name": "Flash"}]}, "mid": {"id": 28790, "name": "Sintax", "level": 9, "cs": 86, "assists": 3, "deaths": 3, "kills": 1, "champion": {"id": 3645, "name": "Taliyah", "slug": "Taliyah", "image_url": "https://cdn-api.pandascore.co/images/lol/champion/image/8fe859d9-af95-4e21-8b1d-9c7c061cd4d2.png"}, "summoner_spells": [{"id": 139, "name": "Teleport"}, {"id": 134, "name": "Flash"}]}, "sup": {"id": 39205, "name": "Lauxio", "level": 7, "cs": 24, "assists": 2, "deaths": 0, "kills": 0, "champion": {"id": 3602, "name": "Nautilus", "slug": "Nautilus", "image_url": "https://cdn-api.pandascore.co/images/lol/champion/image/7f3bc843-2a30-4e14-9cfa-0d8895d2dec4.png"}, "summoner_spells": [{"id": 134, "name": "Flash"}, {"id": 132, "name": "Ignite"}]}, "top": {"id": 37550, "name": "Falleo", "level": 9, "cs": 92, "assists": 0, "deaths": 2, "kills": 1, "champion": {"id": 3703, "name": "Ambessa", "slug": "Ambessa", "image_url": "https://cdn-api.pandascore.co/images/lol/champion/image/4bdc24eb-fcfe-4c11-859e-c76d173aa313.png"}, "summoner_spells": [{"id": 139, "name": "Teleport"}, {"id": 134, "name": "Flash"}]}}, "atakhans": 0, "drakes": 0, "gold": 19799, "heralds": 0, "inhibitors": 0, "nashors": 0, "towers": 0, "voidgrubs": 3, "acronym": "B5"}, "red": {"id": 3340, "name": "Crvena zvezda Esports", "kills": 7, "score": 0, "players": {"adc": {"id": 54354, "name": "Devn", "level": 8, "cs": 106, "assists": 1, "deaths": 0, "kills": 0, "champion": {"id": 3745, "name": "Ezreal", "slug": "Ezreal", "image_url": "https://cdn-api.pandascore.co/images/lol/champion/image/65d28a53-5758-4db1-9d66-d0b68f016ed9.png"}, "summoner_spells": [{"id": 134, "name": "Flash"}, {"id": 129, "name": "Barrier"}]}, "jun": {"id": 32803, "name": "Xeonerr", "level": 8, "cs": 79, "assists": 3, "deaths": 0, "kills": 1, "champion": {"id": 3662, "name": "Vi", "slug": "Vi", "image_url": "https://cdn-api.pandascore.co/images/lol/champion/image/f0e9915e-5f2e-44e9-956d-7b24f4757557.png"}, "summoner_spells": [{"id": 138, "name": "Smite"}, {"id": 134, "name": "Flash"}]}, "mid": {"id": 42195, "name": "Pesho", "level": 10, "cs": 105, "assists": 0, "deaths": 2, "kills": 4, "champion": {"id": 3525, "name": "Aurora", "slug": "Aurora", "image_url": "https://cdn-api.pandascore.co/images/lol/champion/image/fccc9fa8-4ad1-411f-92a0-d43c7b0fc2a0.png"}, "summoner_spells": [{"id": 139, "name": "Teleport"}, {"id": 134, "name": "Flash"}]}, "sup": {"id": 53381, "name": "Zeko", "level": 6, "cs": 18, "assists": 1, "deaths": 1, "kills": 0, "champion": {"id": 3736, "name": "Rell", "slug": "Rell", "image_url": "https://cdn-api.pandascore.co/images/lol/champion/image/04527f37-6ed1-4806-89df-40499a301a24.png"}, "summoner_spells": [{"id": 134, "name": "Flash"}, {"id": 132, "name": "Ignite"}]}, "top": {"id": 52593, "name": "Nenad", "level": 10, "cs": 100, "assists": 0, "deaths": 1, "kills": 2, "champion": {"id": 3630, "name": "Sett", "slug": "Sett", "image_url": "https://cdn-api.pandascore.co/images/lol/champion/image/64d77820-dd57-4ccc-aec1-0492a3e1a74a.png"}, "summoner_spells": [{"id": 139, "name": "Teleport"}, {"id": 134, "name": "Flash"}]}}, "atakhans": 0, "drakes": 1, "gold": 20971, "heralds": 0, "inhibitors": 0, "nashors": 0, "towers": 0, "voidgrubs": 3, "acronym": "CZV"}, "match_id": 1158731, "game_id": 267495, "tournament_id": 16465, "current_timestamp": 720}, {"blue": {"id": 134408, "name": "BeFive", "kills": 5, "score": 0, "players": {"adc": {"id": 18049, "name": "Pl0x", "level": 8, "cs": 117, "assists": 1, "deaths": 1, "kills": 2, "champion": {"id": 3728, "name": "Varus", "slug": "Varus", "image_url": "https://cdn-api.pandascore.co/images/lol/champion/image/b692cde6-0b60-4900-86f3-4f5c36037316.png"}, "summoner_spells": [{"id": 134, "name": "Flash"}, {"id": 129, "name": "Barrier"}]}, "jun": {"id": 7694, "name": "DoubleAiM", "level": 8, "cs": 88, "assists": 1, "deaths": 2, "kills": 1, "champion": {"id": 3666, "name": "Volibear", "slug": "Volibear", "image_url": "https://cdn-api.pandascore.co/images/lol/champion/image/73e72749-ceae-4413-adce-6c1cb863878b.png"}, "summoner_spells": [{"id": 138, "name": "Smite"}, {"id": 134, "name": "Flash"}]}, "mid": {"id": 28790, "name": "Sintax", "level": 9, "cs": 93, "assists": 3, "deaths": 4, "kills": 1, "champion": {"id": 3645, "name": "Taliyah", "slug": "Taliyah", "image_url": "https://cdn-api.pandascore.co/images/lol/champion/image/8fe859d9-af95-4e21-8b1d-9c7c061cd4d2.png"}, "summoner_spells": [{"id": 139, "name": "Teleport"}, {"id": 134, "name": "Flash"}]}, "sup": {"id": 39205, "name": "Lauxio", "level": 7, "cs": 24, "assists": 3, "deaths": 1, "kills": 0, "champion": {"id": 3602, "name": "Nautilus", "slug": "Nautilus", "image_url": "https://cdn-api.pandascore.co/images/lol/champion/image/7f3bc843-2a30-4e14-9cfa-0d8895d2dec4.png"}, "summoner_spells": [{"id": 134, "name": "Flash"}, {"id": 132, "name": "Ignite"}]}, "top": {"id": 37550, "name": "Falleo", "level": 9, "cs": 97, "assists": 0, "deaths": 3, "kills": 1, "champion": {"id": 3703, "name": "Ambessa", "slug": "Ambessa", "image_url": "https://cdn-api.pandascore.co/images/lol/champion/image/4bdc24eb-fcfe-4c11-859e-c76d173aa313.png"}, "summoner_spells": [{"id": 139, "name": "Teleport"}, {"id": 134, "name": "Flash"}]}}, "atakhans": 0, "drakes": 0, "gold": 21511, "heralds": 0, "inhibitors": 0, "nashors": 0, "towers": 0, "voidgrubs": 3, "acronym": "B5"}, "red": {"id": 3340, "name": "Crvena zvezda Esports", "kills": 11, "score": 0, "players": {"adc": {"id": 54354, "name": "Devn", "level": 9, "cs": 115, "assists": 1, "deaths": 0, "kills": 1, "champion": {"id": 3745, "name": "Ezreal", "slug": "Ezreal", "image_url": "https://cdn-api.pandascore.co/images/lol/champion/image/65d28a53-5758-4db1-9d66-d0b68f016ed9.png"}, "summoner_spells": [{"id": 134, "name": "Flash"}, {"id": 129, "name": "Barrier"}]}, "jun": {"id": 32803, "name": "Xeonerr", "level": 9, "cs": 84, "assists": 4, "deaths": 0, "kills": 1, "champion": {"id": 3662, "name": "Vi", "slug": "Vi", "image_url": "https://cdn-api.pandascore.co/images/lol/champion/image/f0e9915e-5f2e-44e9-956d-7b24f4757557.png"}, "summoner_spells": [{"id": 138, "name": "Smite"}, {"id": 134, "name": "Flash"}]}, "mid": {"id": 42195, "name": "Pesho", "level": 11, "cs": 122, "assists": 0, "deaths": 2, "kills": 5, "champion": {"id": 3525, "name": "Aurora", "slug": "Aurora", "image_url": "https://cdn-api.pandascore.co/images/lol/champion/image/fccc9fa8-4ad1-411f-92a0-d43c7b0fc2a0.png"}, "summoner_spells": [{"id": 139, "name": "Teleport"}, {"id": 134, "name": "Flash"}]}, "sup": {"id": 53381, "name": "Zeko", "level": 6, "cs": 18, "assists": 1, "deaths": 2, "kills": 0, "champion": {"id": 3736, "name": "Rell", "slug": "Rell", "image_url": "https://cdn-api.pandascore.co/images/lol/champion/image/04527f37-6ed1-4806-89df-40499a301a24.png"}, "summoner_spells": [{"id": 134, "name": "Flash"}, {"id": 132, "name": "Ignite"}]}, "top": {"id": 52593, "name": "Nenad", "level": 11, "cs": 102, "assists": 0, "deaths": 1, "kills": 4, "champion": {"id": 3630, "name": "Sett", "slug": "Sett", "image_url": "https://cdn-api.pandascore.co/images/lol/champion/image/64d77820-dd57-4ccc-aec1-0492a3e1a74a.png"}, "summoner_spells": [{"id": 139, "name": "Teleport"}, {"id": 134, "name": "Flash"}]}}, "atakhans": 0, "drakes": 2, "gold": 24015, "heralds": 0, "inhibitors": 0, "nashors": 0, "towers": 0, "voidgrubs": 3, "acronym": "CZV"}, "match_id": 1158731, "game_id": 267495, "tournament_id": 16465, "current_timestamp": 780}, {"blue": {"id": 134408, "name": "BeFive", "kills": 5, "score": 0, "players": {"adc": {"id": 18049, "name": "Pl0x", "level": 8, "cs": 125, "assists": 1, "deaths": 1, "kills": 2, "champion": {"id": 3728, "name": "Varus", "slug": "Varus", "image_url": "https://cdn-api.pandascore.co/images/lol/champion/image/b692cde6-0b60-4900-86f3-4f5c36037316.png"}, "summoner_spells": [{"id": 134, "name": "Flash"}, {"id": 129, "name": "Barrier"}]}, "jun": {"id": 7694, "name": "DoubleAiM", "level": 9, "cs": 96, "assists": 1, "deaths": 2, "kills": 1, "champion": {"id": 3666, "name": "Volibear", "slug": "Volibear", "image_url": "https://cdn-api.pandascore.co/images/lol/champion/image/73e72749-ceae-4413-adce-6c1cb863878b.png"}, "summoner_spells": [{"id": 138, "name": "Smite"}, {"id": 134, "name": "Flash"}]}, "mid": {"id": 28790, "name": "Sintax", "level": 10, "cs": 98, "assists": 3, "deaths": 4, "kills": 1, "champion": {"id": 3645, "name": "Taliyah", "slug": "Taliyah", "image_url": "https://cdn-api.pandascore.co/images/lol/champion/image/8fe859d9-af95-4e21-8b1d-9c7c061cd4d2.png"}, "summoner_spells": [{"id": 139, "name": "Teleport"}, {"id": 134, "name": "Flash"}]}, "sup": {"id": 39205, "name": "Lauxio", "level": 7, "cs": 26, "assists": 3, "deaths": 1, "kills": 0, "champion": {"id": 3602, "name": "Nautilus", "slug": "Nautilus", "image_url": "https://cdn-api.pandascore.co/images/lol/champion/image/7f3bc843-2a30-4e14-9cfa-0d8895d2dec4.png"}, "summoner_spells": [{"id": 134, "name": "Flash"}, {"id": 132, "name": "Ignite"}]}, "top": {"id": 37550, "name": "Falleo", "level": 10, "cs": 108, "assists": 0, "deaths": 3, "kills": 1, "champion": {"id": 3703, "name": "Ambessa", "slug": "Ambessa", "image_url": "https://cdn-api.pandascore.co/images/lol/champion/image/4bdc24eb-fcfe-4c11-859e-c76d173aa313.png"}, "summoner_spells": [{"id": 139, "name": "Teleport"}, {"id": 134, "name": "Flash"}]}}, "atakhans": 0, "drakes": 0, "gold": 23033, "heralds": 0, "inhibitors": 0, "nashors": 0, "towers": 0, "voidgrubs": 3, "acronym": "B5"}, "red": {"id": 3340, "name": "Crvena zvezda Esports", "kills": 11, "score": 0, "players": {"adc": {"id": 54354, "name": "Devn", "level": 9, "cs": 126, "assists": 1, "deaths": 0, "kills": 1, "champion": {"id": 3745, "name": "Ezreal", "slug": "Ezreal", "image_url": "https://cdn-api.pandascore.co/images/lol/champion/image/65d28a53-5758-4db1-9d66-d0b68f016ed9.png"}, "summoner_spells": [{"id": 134, "name": "Flash"}, {"id": 129, "name": "Barrier"}]}, "jun": {"id": 32803, "name": "Xeonerr", "level": 10, "cs": 104, "assists": 4, "deaths": 0, "kills": 1, "champion": {"id": 3662, "name": "Vi", "slug": "Vi", "image_url": "https://cdn-api.pandascore.co/images/lol/champion/image/f0e9915e-5f2e-44e9-956d-7b24f4757557.png"}, "summoner_spells": [{"id": 138, "name": "Smite"}, {"id": 134, "name": "Flash"}]}, "mid": {"id": 42195, "name": "Pesho", "level": 11, "cs": 127, "assists": 0, "deaths": 2, "kills": 5, "champion": {"id": 3525, "name": "Aurora", "slug": "Aurora", "image_url": "https://cdn-api.pandascore.co/images/lol/champion/image/fccc9fa8-4ad1-411f-92a0-d43c7b0fc2a0.png"}, "summoner_spells": [{"id": 139, "name": "Teleport"}, {"id": 134, "name": "Flash"}]}, "sup": {"id": 53381, "name": "Zeko", "level": 6, "cs": 19, "assists": 1, "deaths": 2, "kills": 0, "champion": {"id": 3736, "name": "Rell", "slug": "Rell", "image_url": "https://cdn-api.pandascore.co/images/lol/champion/image/04527f37-6ed1-4806-89df-40499a301a24.png"}, "summoner_spells": [{"id": 134, "name": "Flash"}, {"id": 132, "name": "Ignite"}]}, "top": {"id": 52593, "name": "Nenad", "level": 11, "cs": 114, "assists": 0, "deaths": 1, "kills": 4, "champion": {"id": 3630, "name": "Sett", "slug": "Sett", "image_url": "https://cdn-api.pandascore.co/images/lol/champion/image/64d77820-dd57-4ccc-aec1-0492a3e1a74a.png"}, "summoner_spells": [{"id": 139, "name": "Teleport"}, {"id": 134, "name": "Flash"}]}}, "atakhans": 0, "drakes": 2, "gold": 25897, "heralds": 0, "inhibitors": 0, "nashors": 0, "towers": 0, "voidgrubs": 3, "acronym": "CZV"}, "match_id": 1158731, "game_id": 267495, "tournament_id": 16465, "current_timestamp": 840}, {"blue": {"id": 134408, "name": "BeFive", "kills": 5, "score": 0, "players": {"adc": {"id": 18049, "name": "Pl0x", "level": 9, "cs": 128, "assists": 1, "deaths": 2, "kills": 2, "champion": {"id": 3728, "name": "Varus", "slug": "Varus", "image_url": "https://cdn-api.pandascore.co/images/lol/champion/image/b692cde6-0b60-4900-86f3-4f5c36037316.png"}, "summoner_spells": [{"id": 134, "name": "Flash"}, {"id": 129, "name": "Barrier"}]}, "jun": {"id": 7694, "name": "DoubleAiM", "level": 9, "cs": 105, "assists": 1, "deaths": 2, "kills": 1, "champion": {"id": 3666, "name": "Volibear", "slug": "Volibear", "image_url": "https://cdn-api.pandascore.co/images/lol/champion/image/73e72749-ceae-4413-adce-6c1cb863878b.png"}, "summoner_spells": [{"id": 138, "name": "Smite"}, {"id": 134, "name": "Flash"}]}, "mid": {"id": 28790, "name": "Sintax", "level": 10, "cs": 109, "assists": 3, "deaths": 4, "kills": 1, "champion": {"id": 3645, "name": "Taliyah", "slug": "Taliyah", "image_url": "https://cdn-api.pandascore.co/images/lol/champion/image/8fe859d9-af95-4e21-8b1d-9c7c061cd4d2.png"}, "summoner_spells": [{"id": 139, "name": "Teleport"}, {"id": 134, "name": "Flash"}]}, "sup": {"id": 39205, "name": "Lauxio", "level": 8, "cs": 27, "assists": 3, "deaths": 1, "kills": 0, "champion": {"id": 3602, "name": "Nautilus", "slug": "Nautilus", "image_url": "https://cdn-api.pandascore.co/images/lol/champion/image/7f3bc843-2a30-4e14-9cfa-0d8895d2dec4.png"}, "summoner_spells": [{"id": 134, "name": "Flash"}, {"id": 132, "name": "Ignite"}]}, "top": {"id": 37550, "name": "Falleo", "level": 11, "cs": 119, "assists": 0, "deaths": 3, "kills": 1, "champion": {"id": 3703, "name": "Ambessa", "slug": "Ambessa", "image_url": "https://cdn-api.pandascore.co/images/lol/champion/image/4bdc24eb-fcfe-4c11-859e-c76d173aa313.png"}, "summoner_spells": [{"id": 139, "name": "Teleport"}, {"id": 134, "name": "Flash"}]}}, "atakhans": 0, "drakes": 0, "gold": 24384, "heralds": 0, "inhibitors": 0, "nashors": 0, "towers": 0, "voidgrubs": 3, "acronym": "B5"}, "red": {"id": 3340, "name": "Crvena zvezda Esports", "kills": 12, "score": 0, "players": {"adc": {"id": 54354, "name": "Devn", "level": 10, "cs": 137, "assists": 1, "deaths": 0, "kills": 1, "champion": {"id": 3745, "name": "Ezreal", "slug": "Ezreal", "image_url": "https://cdn-api.pandascore.co/images/lol/champion/image/65d28a53-5758-4db1-9d66-d0b68f016ed9.png"}, "summoner_spells": [{"id": 134, "name": "Flash"}, {"id": 129, "name": "Barrier"}]}, "jun": {"id": 32803, "name": "Xeonerr", "level": 10, "cs": 109, "assists": 4, "deaths": 0, "kills": 1, "champion": {"id": 3662, "name": "Vi", "slug": "Vi", "image_url": "https://cdn-api.pandascore.co/images/lol/champion/image/f0e9915e-5f2e-44e9-956d-7b24f4757557.png"}, "summoner_spells": [{"id": 138, "name": "Smite"}, {"id": 134, "name": "Flash"}]}, "mid": {"id": 42195, "name": "Pesho", "level": 12, "cs": 137, "assists": 0, "deaths": 2, "kills": 6, "champion": {"id": 3525, "name": "Aurora", "slug": "Aurora", "image_url": "https://cdn-api.pandascore.co/images/lol/champion/image/fccc9fa8-4ad1-411f-92a0-d43c7b0fc2a0.png"}, "summoner_spells": [{"id": 139, "name": "Teleport"}, {"id": 134, "name": "Flash"}]}, "sup": {"id": 53381, "name": "Zeko", "level": 6, "cs": 20, "assists": 1, "deaths": 2, "kills": 0, "champion": {"id": 3736, "name": "Rell", "slug": "Rell", "image_url": "https://cdn-api.pandascore.co/images/lol/champion/image/04527f37-6ed1-4806-89df-40499a301a24.png"}, "summoner_spells": [{"id": 134, "name": "Flash"}, {"id": 132, "name": "Ignite"}]}, "top": {"id": 52593, "name": "Nenad", "level": 12, "cs": 125, "assists": 0, "deaths": 1, "kills": 4, "champion": {"id": 3630, "name": "Sett", "slug": "Sett", "image_url": "https://cdn-api.pandascore.co/images/lol/champion/image/64d77820-dd57-4ccc-aec1-0492a3e1a74a.png"}, "summoner_spells": [{"id": 139, "name": "Teleport"}, {"id": 134, "name": "Flash"}]}}, "atakhans": 0, "drakes": 2, "gold": 27653, "heralds": 0, "inhibitors": 0, "nashors": 0, "towers": 0, "voidgrubs": 3, "acronym": "CZV"}, "match_id": 1158731, "game_id": 267495, "tournament_id": 16465, "current_timestamp": 900}, {"blue": {"id": 134408, "name": "BeFive", "kills": 6, "score": 0, "players": {"adc": {"id": 18049, "name": "Pl0x", "level": 9, "cs": 138, "assists": 1, "deaths": 2, "kills": 2, "champion": {"id": 3728, "name": "Varus", "slug": "Varus", "image_url": "https://cdn-api.pandascore.co/images/lol/champion/image/b692cde6-0b60-4900-86f3-4f5c36037316.png"}, "summoner_spells": [{"id": 134, "name": "Flash"}, {"id": 129, "name": "Barrier"}]}, "jun": {"id": 7694, "name": "DoubleAiM", "level": 10, "cs": 109, "assists": 2, "deaths": 2, "kills": 1, "champion": {"id": 3666, "name": "Volibear", "slug": "Volibear", "image_url": "https://cdn-api.pandascore.co/images/lol/champion/image/73e72749-ceae-4413-adce-6c1cb863878b.png"}, "summoner_spells": [{"id": 138, "name": "Smite"}, {"id": 134, "name": "Flash"}]}, "mid": {"id": 28790, "name": "Sintax", "level": 11, "cs": 119, "assists": 3, "deaths": 4, "kills": 2, "champion": {"id": 3645, "name": "Taliyah", "slug": "Taliyah", "image_url": "https://cdn-api.pandascore.co/images/lol/champion/image/8fe859d9-af95-4e21-8b1d-9c7c061cd4d2.png"}, "summoner_spells": [{"id": 139, "name": "Teleport"}, {"id": 134, "name": "Flash"}]}, "sup": {"id": 39205, "name": "Lauxio", "level": 8, "cs": 27, "assists": 4, "deaths": 2, "kills": 0, "champion": {"id": 3602, "name": "Nautilus", "slug": "Nautilus", "image_url": "https://cdn-api.pandascore.co/images/lol/champion/image/7f3bc843-2a30-4e14-9cfa-0d8895d2dec4.png"}, "summoner_spells": [{"id": 134, "name": "Flash"}, {"id": 132, "name": "Ignite"}]}, "top": {"id": 37550, "name": "Falleo", "level": 11, "cs": 119, "assists": 1, "deaths": 3, "kills": 1, "champion": {"id": 3703, "name": "Ambessa", "slug": "Ambessa", "image_url": "https://cdn-api.pandascore.co/images/lol/champion/image/4bdc24eb-fcfe-4c11-859e-c76d173aa313.png"}, "summoner_spells": [{"id": 139, "name": "Teleport"}, {"id": 134, "name": "Flash"}]}}, "atakhans": 0, "drakes": 0, "gold": 26335, "heralds": 0, "inhibitors": 0, "nashors": 0, "towers": 0, "voidgrubs": 3, "acronym": "B5"}, "red": {"id": 3340, "name": "Crvena zvezda Esports", "kills": 13, "score": 0, "players": {"adc": {"id": 54354, "name": "Devn", "level": 10, "cs": 145, "assists": 1, "deaths": 0, "kills": 2, "champion": {"id": 3745, "name": "Ezreal", "slug": "Ezreal", "image_url": "https://cdn-api.pandascore.co/images/lol/champion/image/65d28a53-5758-4db1-9d66-d0b68f016ed9.png"}, "summoner_spells": [{"id": 134, "name": "Flash"}, {"id": 129, "name": "Barrier"}]}, "jun": {"id": 32803, "name": "Xeonerr", "level": 10, "cs": 109, "assists": 4, "deaths": 1, "kills": 1, "champion": {"id": 3662, "name": "Vi", "slug": "Vi", "image_url": "https://cdn-api.pandascore.co/images/lol/champion/image/f0e9915e-5f2e-44e9-956d-7b24f4757557.png"}, "summoner_spells": [{"id": 138, "name": "Smite"}, {"id": 134, "name": "Flash"}]}, "mid": {"id": 42195, "name": "Pesho", "level": 12, "cs": 150, "assists": 0, "deaths": 2, "kills": 6, "champion": {"id": 3525, "name": "Aurora", "slug": "Aurora", "image_url": "https://cdn-api.pandascore.co/images/lol/champion/image/fccc9fa8-4ad1-411f-92a0-d43c7b0fc2a0.png"}, "summoner_spells": [{"id": 139, "name": "Teleport"}, {"id": 134, "name": "Flash"}]}, "sup": {"id": 53381, "name": "Zeko", "level": 6, "cs": 20, "assists": 2, "deaths": 2, "kills": 0, "champion": {"id": 3736, "name": "Rell", "slug": "Rell", "image_url": "https://cdn-api.pandascore.co/images/lol/champion/image/04527f37-6ed1-4806-89df-40499a301a24.png"}, "summoner_spells": [{"id": 134, "name": "Flash"}, {"id": 132, "name": "Ignite"}]}, "top": {"id": 52593, "name": "Nenad", "level": 12, "cs": 134, "assists": 1, "deaths": 1, "kills": 4, "champion": {"id": 3630, "name": "Sett", "slug": "Sett", "image_url": "https://cdn-api.pandascore.co/images/lol/champion/image/64d77820-dd57-4ccc-aec1-0492a3e1a74a.png"}, "summoner_spells": [{"id": 139, "name": "Teleport"}, {"id": 134, "name": "Flash"}]}}, "atakhans": 0, "drakes": 2, "gold": 29541, "heralds": 0, "inhibitors": 0, "nashors": 0, "towers": 0, "voidgrubs": 3, "acronym": "CZV"}, "match_id": 1158731, "game_id": 267495, "tournament_id": 16465, "current_timestamp": 960}, {"blue": {"id": 134408, "name": "BeFive", "kills": 6, "score": 0, "players": {"adc": {"id": 18049, "name": "Pl0x", "level": 9, "cs": 141, "assists": 1, "deaths": 3, "kills": 2, "champion": {"id": 3728, "name": "Varus", "slug": "Varus", "image_url": "https://cdn-api.pandascore.co/images/lol/champion/image/b692cde6-0b60-4900-86f3-4f5c36037316.png"}, "summoner_spells": [{"id": 134, "name": "Flash"}, {"id": 129, "name": "Barrier"}]}, "jun": {"id": 7694, "name": "DoubleAiM", "level": 10, "cs": 115, "assists": 2, "deaths": 3, "kills": 1, "champion": {"id": 3666, "name": "Volibear", "slug": "Volibear", "image_url": "https://cdn-api.pandascore.co/images/lol/champion/image/73e72749-ceae-4413-adce-6c1cb863878b.png"}, "summoner_spells": [{"id": 138, "name": "Smite"}, {"id": 134, "name": "Flash"}]}, "mid": {"id": 28790, "name": "Sintax", "level": 11, "cs": 129, "assists": 3, "deaths": 4, "kills": 2, "champion": {"id": 3645, "name": "Taliyah", "slug": "Taliyah", "image_url": "https://cdn-api.pandascore.co/images/lol/champion/image/8fe859d9-af95-4e21-8b1d-9c7c061cd4d2.png"}, "summoner_spells": [{"id": 139, "name": "Teleport"}, {"id": 134, "name": "Flash"}]}, "sup": {"id": 39205, "name": "Lauxio", "level": 8, "cs": 28, "assists": 4, "deaths": 2, "kills": 0, "champion": {"id": 3602, "name": "Nautilus", "slug": "Nautilus", "image_url": "https://cdn-api.pandascore.co/images/lol/champion/image/7f3bc843-2a30-4e14-9cfa-0d8895d2dec4.png"}, "summoner_spells": [{"id": 134, "name": "Flash"}, {"id": 132, "name": "Ignite"}]}, "top": {"id": 37550, "name": "Falleo", "level": 11, "cs": 129, "assists": 1, "deaths": 4, "kills": 1, "champion": {"id": 3703, "name": "Ambessa", "slug": "Ambessa", "image_url": "https://cdn-api.pandascore.co/images/lol/champion/image/4bdc24eb-fcfe-4c11-859e-c76d173aa313.png"}, "summoner_spells": [{"id": 139, "name": "Teleport"}, {"id": 134, "name": "Flash"}]}}, "atakhans": 0, "drakes": 0, "gold": 28105, "heralds": 0, "inhibitors": 0, "nashors": 0, "towers": 0, "voidgrubs": 3, "acronym": "B5"}, "red": {"id": 3340, "name": "Crvena zvezda Esports", "kills": 16, "score": 0, "players": {"adc": {"id": 54354, "name": "Devn", "level": 11, "cs": 158, "assists": 3, "deaths": 0, "kills": 2, "champion": {"id": 3745, "name": "Ezreal", "slug": "Ezreal", "image_url": "https://cdn-api.pandascore.co/images/lol/champion/image/65d28a53-5758-4db1-9d66-d0b68f016ed9.png"}, "summoner_spells": [{"id": 134, "name": "Flash"}, {"id": 129, "name": "Barrier"}]}, "jun": {"id": 32803, "name": "Xeonerr", "level": 11, "cs": 109, "assists": 4, "deaths": 1, "kills": 4, "champion": {"id": 3662, "name": "Vi", "slug": "Vi", "image_url": "https://cdn-api.pandascore.co/images/lol/champion/image/f0e9915e-5f2e-44e9-956d-7b24f4757557.png"}, "summoner_spells": [{"id": 138, "name": "Smite"}, {"id": 134, "name": "Flash"}]}, "mid": {"id": 42195, "name": "Pesho", "level": 13, "cs": 164, "assists": 0, "deaths": 2, "kills": 6, "champion": {"id": 3525, "name": "Aurora", "slug": "Aurora", "image_url": "https://cdn-api.pandascore.co/images/lol/champion/image/fccc9fa8-4ad1-411f-92a0-d43c7b0fc2a0.png"}, "summoner_spells": [{"id": 139, "name": "Teleport"}, {"id": 134, "name": "Flash"}]}, "sup": {"id": 53381, "name": "Zeko", "level": 8, "cs": 20, "assists": 5, "deaths": 2, "kills": 0, "champion": {"id": 3736, "name": "Rell", "slug": "Rell", "image_url": "https://cdn-api.pandascore.co/images/lol/champion/image/04527f37-6ed1-4806-89df-40499a301a24.png"}, "summoner_spells": [{"id": 134, "name": "Flash"}, {"id": 132, "name": "Ignite"}]}, "top": {"id": 52593, "name": "Nenad", "level": 13, "cs": 148, "assists": 1, "deaths": 1, "kills": 4, "champion": {"id": 3630, "name": "Sett", "slug": "Sett", "image_url": "https://cdn-api.pandascore.co/images/lol/champion/image/64d77820-dd57-4ccc-aec1-0492a3e1a74a.png"}, "summoner_spells": [{"id": 139, "name": "Teleport"}, {"id": 134, "name": "Flash"}]}}, "atakhans": 0, "drakes": 2, "gold": 33591, "heralds": 0, "inhibitors": 0, "nashors": 0, "towers": 2, "voidgrubs": 3, "acronym": "CZV"}, "match_id": 1158731, "game_id": 267495, "tournament_id": 16465, "current_timestamp": 1020}, {"blue": {"id": 134408, "name": "BeFive", "kills": 6, "score": 0, "players": {"adc": {"id": 18049, "name": "Pl0x", "level": 10, "cs": 153, "assists": 1, "deaths": 3, "kills": 2, "champion": {"id": 3728, "name": "Varus", "slug": "Varus", "image_url": "https://cdn-api.pandascore.co/images/lol/champion/image/b692cde6-0b60-4900-86f3-4f5c36037316.png"}, "summoner_spells": [{"id": 134, "name": "Flash"}, {"id": 129, "name": "Barrier"}]}, "jun": {"id": 7694, "name": "DoubleAiM", "level": 11, "cs": 123, "assists": 2, "deaths": 3, "kills": 1, "champion": {"id": 3666, "name": "Volibear", "slug": "Volibear", "image_url": "https://cdn-api.pandascore.co/images/lol/champion/image/73e72749-ceae-4413-adce-6c1cb863878b.png"}, "summoner_spells": [{"id": 138, "name": "Smite"}, {"id": 134, "name": "Flash"}]}, "mid": {"id": 28790, "name": "Sintax", "level": 12, "cs": 142, "assists": 3, "deaths": 4, "kills": 2, "champion": {"id": 3645, "name": "Taliyah", "slug": "Taliyah", "image_url": "https://cdn-api.pandascore.co/images/lol/champion/image/8fe859d9-af95-4e21-8b1d-9c7c061cd4d2.png"}, "summoner_spells": [{"id": 139, "name": "Teleport"}, {"id": 134, "name": "Flash"}]}, "sup": {"id": 39205, "name": "Lauxio", "level": 9, "cs": 29, "assists": 4, "deaths": 2, "kills": 0, "champion": {"id": 3602, "name": "Nautilus", "slug": "Nautilus", "image_url": "https://cdn-api.pandascore.co/images/lol/champion/image/7f3bc843-2a30-4e14-9cfa-0d8895d2dec4.png"}, "summoner_spells": [{"id": 134, "name": "Flash"}, {"id": 132, "name": "Ignite"}]}, "top": {"id": 37550, "name": "Falleo", "level": 11, "cs": 138, "assists": 1, "deaths": 4, "kills": 1, "champion": {"id": 3703, "name": "Ambessa", "slug": "Ambessa", "image_url": "https://cdn-api.pandascore.co/images/lol/champion/image/4bdc24eb-fcfe-4c11-859e-c76d173aa313.png"}, "summoner_spells": [{"id": 139, "name": "Teleport"}, {"id": 134, "name": "Flash"}]}}, "atakhans": 0, "drakes": 0, "gold": 29693, "heralds": 0, "inhibitors": 0, "nashors": 0, "towers": 0, "voidgrubs": 3, "acronym": "B5"}, "red": {"id": 3340, "name": "Crvena zvezda Esports", "kills": 16, "score": 0, "players": {"adc": {"id": 54354, "name": "Devn", "level": 11, "cs": 160, "assists": 3, "deaths": 0, "kills": 2, "champion": {"id": 3745, "name": "Ezreal", "slug": "Ezreal", "image_url": "https://cdn-api.pandascore.co/images/lol/champion/image/65d28a53-5758-4db1-9d66-d0b68f016ed9.png"}, "summoner_spells": [{"id": 134, "name": "Flash"}, {"id": 129, "name": "Barrier"}]}, "jun": {"id": 32803, "name": "Xeonerr", "level": 11, "cs": 118, "assists": 4, "deaths": 1, "kills": 4, "champion": {"id": 3662, "name": "Vi", "slug": "Vi", "image_url": "https://cdn-api.pandascore.co/images/lol/champion/image/f0e9915e-5f2e-44e9-956d-7b24f4757557.png"}, "summoner_spells": [{"id": 138, "name": "Smite"}, {"id": 134, "name": "Flash"}]}, "mid": {"id": 42195, "name": "Pesho", "level": 13, "cs": 178, "assists": 0, "deaths": 2, "kills": 6, "champion": {"id": 3525, "name": "Aurora", "slug": "Aurora", "image_url": "https://cdn-api.pandascore.co/images/lol/champion/image/fccc9fa8-4ad1-411f-92a0-d43c7b0fc2a0.png"}, "summoner_spells": [{"id": 139, "name": "Teleport"}, {"id": 134, "name": "Flash"}]}, "sup": {"id": 53381, "name": "Zeko", "level": 8, "cs": 22, "assists": 5, "deaths": 2, "kills": 0, "champion": {"id": 3736, "name": "Rell", "slug": "Rell", "image_url": "https://cdn-api.pandascore.co/images/lol/champion/image/04527f37-6ed1-4806-89df-40499a301a24.png"}, "summoner_spells": [{"id": 134, "name": "Flash"}, {"id": 132, "name": "Ignite"}]}, "top": {"id": 52593, "name": "Nenad", "level": 13, "cs": 154, "assists": 1, "deaths": 1, "kills": 4, "champion": {"id": 3630, "name": "Sett", "slug": "Sett", "image_url": "https://cdn-api.pandascore.co/images/lol/champion/image/64d77820-dd57-4ccc-aec1-0492a3e1a74a.png"}, "summoner_spells": [{"id": 139, "name": "Teleport"}, {"id": 134, "name": "Flash"}]}}, "atakhans": 0, "drakes": 3, "gold": 34993, "heralds": 0, "inhibitors": 0, "nashors": 0, "towers": 2, "voidgrubs": 3, "acronym": "CZV"}, "match_id": 1158731, "game_id": 267495, "tournament_id": 16465, "current_timestamp": 1080}, {"blue": {"id": 134408, "name": "BeFive", "kills": 6, "score": 0, "players": {"adc": {"id": 18049, "name": "Pl0x", "level": 10, "cs": 164, "assists": 1, "deaths": 3, "kills": 2, "champion": {"id": 3728, "name": "Varus", "slug": "Varus", "image_url": "https://cdn-api.pandascore.co/images/lol/champion/image/b692cde6-0b60-4900-86f3-4f5c36037316.png"}, "summoner_spells": [{"id": 134, "name": "Flash"}, {"id": 129, "name": "Barrier"}]}, "jun": {"id": 7694, "name": "DoubleAiM", "level": 11, "cs": 135, "assists": 2, "deaths": 3, "kills": 1, "champion": {"id": 3666, "name": "Volibear", "slug": "Volibear", "image_url": "https://cdn-api.pandascore.co/images/lol/champion/image/73e72749-ceae-4413-adce-6c1cb863878b.png"}, "summoner_spells": [{"id": 138, "name": "Smite"}, {"id": 134, "name": "Flash"}]}, "mid": {"id": 28790, "name": "Sintax", "level": 12, "cs": 154, "assists": 3, "deaths": 4, "kills": 2, "champion": {"id": 3645, "name": "Taliyah", "slug": "Taliyah", "image_url": "https://cdn-api.pandascore.co/images/lol/champion/image/8fe859d9-af95-4e21-8b1d-9c7c061cd4d2.png"}, "summoner_spells": [{"id": 139, "name": "Teleport"}, {"id": 134, "name": "Flash"}]}, "sup": {"id": 39205, "name": "Lauxio", "level": 9, "cs": 29, "assists": 4, "deaths": 2, "kills": 0, "champion": {"id": 3602, "name": "Nautilus", "slug": "Nautilus", "image_url": "https://cdn-api.pandascore.co/images/lol/champion/image/7f3bc843-2a30-4e14-9cfa-0d8895d2dec4.png"}, "summoner_spells": [{"id": 134, "name": "Flash"}, {"id": 132, "name": "Ignite"}]}, "top": {"id": 37550, "name": "Falleo", "level": 12, "cs": 144, "assists": 1, "deaths": 4, "kills": 1, "champion": {"id": 3703, "name": "Ambessa", "slug": "Ambessa", "image_url": "https://cdn-api.pandascore.co/images/lol/champion/image/4bdc24eb-fcfe-4c11-859e-c76d173aa313.png"}, "summoner_spells": [{"id": 139, "name": "Teleport"}, {"id": 134, "name": "Flash"}]}}, "atakhans": 0, "drakes": 0, "gold": 31353, "heralds": 0, "inhibitors": 0, "nashors": 0, "towers": 0, "voidgrubs": 3, "acronym": "B5"}, "red": {"id": 3340, "name": "Crvena zvezda Esports", "kills": 16, "score": 0, "players": {"adc": {"id": 54354, "name": "Devn", "level": 12, "cs": 174, "assists": 3, "deaths": 0, "kills": 2, "champion": {"id": 3745, "name": "Ezreal", "slug": "Ezreal", "image_url": "https://cdn-api.pandascore.co/images/lol/champion/image/65d28a53-5758-4db1-9d66-d0b68f016ed9.png"}, "summoner_spells": [{"id": 134, "name": "Flash"}, {"id": 129, "name": "Barrier"}]}, "jun": {"id": 32803, "name": "Xeonerr", "level": 12, "cs": 126, "assists": 4, "deaths": 1, "kills": 4, "champion": {"id": 3662, "name": "Vi", "slug": "Vi", "image_url": "https://cdn-api.pandascore.co/images/lol/champion/image/f0e9915e-5f2e-44e9-956d-7b24f4757557.png"}, "summoner_spells": [{"id": 138, "name": "Smite"}, {"id": 134, "name": "Flash"}]}, "mid": {"id": 42195, "name": "Pesho", "level": 14, "cs": 197, "assists": 0, "deaths": 2, "kills": 6, "champion": {"id": 3525, "name": "Aurora", "slug": "Aurora", "image_url": "https://cdn-api.pandascore.co/images/lol/champion/image/fccc9fa8-4ad1-411f-92a0-d43c7b0fc2a0.png"}, "summoner_spells": [{"id": 139, "name": "Teleport"}, {"id": 134, "name": "Flash"}]}, "sup": {"id": 53381, "name": "Zeko", "level": 8, "cs": 22, "assists": 5, "deaths": 2, "kills": 0, "champion": {"id": 3736, "name": "Rell", "slug": "Rell", "image_url": "https://cdn-api.pandascore.co/images/lol/champion/image/04527f37-6ed1-4806-89df-40499a301a24.png"}, "summoner_spells": [{"id": 134, "name": "Flash"}, {"id": 132, "name": "Ignite"}]}, "top": {"id": 52593, "name": "Nenad", "level": 13, "cs": 166, "assists": 1, "deaths": 1, "kills": 4, "champion": {"id": 3630, "name": "Sett", "slug": "Sett", "image_url": "https://cdn-api.pandascore.co/images/lol/champion/image/64d77820-dd57-4ccc-aec1-0492a3e1a74a.png"}, "summoner_spells": [{"id": 139, "name": "Teleport"}, {"id": 134, "name": "Flash"}]}}, "atakhans": 0, "drakes": 3, "gold": 37751, "heralds": 1, "inhibitors": 0, "nashors": 0, "towers": 3, "voidgrubs": 3, "acronym": "CZV"}, "match_id": 1158731, "game_id": 267495, "tournament_id": 16465, "current_timestamp": 1140}, {"blue": {"id": 134408, "name": "BeFive", "kills": 9, "score": 0, "players": {"adc": {"id": 18049, "name": "Pl0x", "level": 11, "cs": 164, "assists": 3, "deaths": 4, "kills": 2, "champion": {"id": 3728, "name": "Varus", "slug": "Varus", "image_url": "https://cdn-api.pandascore.co/images/lol/champion/image/b692cde6-0b60-4900-86f3-4f5c36037316.png"}, "summoner_spells": [{"id": 134, "name": "Flash"}, {"id": 129, "name": "Barrier"}]}, "jun": {"id": 7694, "name": "DoubleAiM", "level": 12, "cs": 142, "assists": 2, "deaths": 3, "kills": 2, "champion": {"id": 3666, "name": "Volibear", "slug": "Volibear", "image_url": "https://cdn-api.pandascore.co/images/lol/champion/image/73e72749-ceae-4413-adce-6c1cb863878b.png"}, "summoner_spells": [{"id": 138, "name": "Smite"}, {"id": 134, "name": "Flash"}]}, "mid": {"id": 28790, "name": "Sintax", "level": 12, "cs": 157, "assists": 3, "deaths": 5, "kills": 3, "champion": {"id": 3645, "name": "Taliyah", "slug": "Taliyah", "image_url": "https://cdn-api.pandascore.co/images/lol/champion/image/8fe859d9-af95-4e21-8b1d-9c7c061cd4d2.png"}, "summoner_spells": [{"id": 139, "name": "Teleport"}, {"id": 134, "name": "Flash"}]}, "sup": {"id": 39205, "name": "Lauxio", "level": 9, "cs": 30, "assists": 6, "deaths": 3, "kills": 0, "champion": {"id": 3602, "name": "Nautilus", "slug": "Nautilus", "image_url": "https://cdn-api.pandascore.co/images/lol/champion/image/7f3bc843-2a30-4e14-9cfa-0d8895d2dec4.png"}, "summoner_spells": [{"id": 134, "name": "Flash"}, {"id": 132, "name": "Ignite"}]}, "top": {"id": 37550, "name": "Falleo", "level": 13, "cs": 158, "assists": 1, "deaths": 4, "kills": 2, "champion": {"id": 3703, "name": "Ambessa", "slug": "Ambessa", "image_url": "https://cdn-api.pandascore.co/images/lol/champion/image/4bdc24eb-fcfe-4c11-859e-c76d173aa313.png"}, "summoner_spells": [{"id": 139, "name": "Teleport"}, {"id": 134, "name": "Flash"}]}}, "atakhans": 0, "drakes": 0, "gold": 34451, "heralds": 0, "inhibitors": 0, "nashors": 0, "towers": 0, "voidgrubs": 3, "acronym": "B5"}, "red": {"id": 3340, "name": "Crvena zvezda Esports", "kills": 19, "score": 0, "players": {"adc": {"id": 54354, "name": "Devn", "level": 12, "cs": 175, "assists": 4, "deaths": 1, "kills": 2, "champion": {"id": 3745, "name": "Ezreal", "slug": "Ezreal", "image_url": "https://cdn-api.pandascore.co/images/lol/champion/image/65d28a53-5758-4db1-9d66-d0b68f016ed9.png"}, "summoner_spells": [{"id": 134, "name": "Flash"}, {"id": 129, "name": "Barrier"}]}, "jun": {"id": 32803, "name": "Xeonerr", "level": 12, "cs": 127, "assists": 4, "deaths": 1, "kills": 6, "champion": {"id": 3662, "name": "Vi", "slug": "Vi", "image_url": "https://cdn-api.pandascore.co/images/lol/champion/image/f0e9915e-5f2e-44e9-956d-7b24f4757557.png"}, "summoner_spells": [{"id": 138, "name": "Smite"}, {"id": 134, "name": "Flash"}]}, "mid": {"id": 42195, "name": "Pesho", "level": 14, "cs": 207, "assists": 1, "deaths": 2, "kills": 7, "champion": {"id": 3525, "name": "Aurora", "slug": "Aurora", "image_url": "https://cdn-api.pandascore.co/images/lol/champion/image/fccc9fa8-4ad1-411f-92a0-d43c7b0fc2a0.png"}, "summoner_spells": [{"id": 139, "name": "Teleport"}, {"id": 134, "name": "Flash"}]}, "sup": {"id": 53381, "name": "Zeko", "level": 9, "cs": 22, "assists": 8, "deaths": 3, "kills": 0, "champion": {"id": 3736, "name": "Rell", "slug": "Rell", "image_url": "https://cdn-api.pandascore.co/images/lol/champion/image/04527f37-6ed1-4806-89df-40499a301a24.png"}, "summoner_spells": [{"id": 134, "name": "Flash"}, {"id": 132, "name": "Ignite"}]}, "top": {"id": 52593, "name": "Nenad", "level": 14, "cs": 179, "assists": 1, "deaths": 2, "kills": 4, "champion": {"id": 3630, "name": "Sett", "slug": "Sett", "image_url": "https://cdn-api.pandascore.co/images/lol/champion/image/64d77820-dd57-4ccc-aec1-0492a3e1a74a.png"}, "summoner_spells": [{"id": 139, "name": "Teleport"}, {"id": 134, "name": "Flash"}]}}, "atakhans": 0, "drakes": 3, "gold": 40811, "heralds": 1, "inhibitors": 0, "nashors": 0, "towers": 4, "voidgrubs": 3, "acronym": "CZV"}, "match_id": 1158731, "game_id": 267495, "tournament_id": 16465, "current_timestamp": 1200}, {"blue": {"id": 134408, "name": "BeFive", "kills": 9, "score": 0, "players": {"adc": {"id": 18049, "name": "Pl0x", "level": 11, "cs": 177, "assists": 3, "deaths": 4, "kills": 2, "champion": {"id": 3728, "name": "Varus", "slug": "Varus", "image_url": "https://cdn-api.pandascore.co/images/lol/champion/image/b692cde6-0b60-4900-86f3-4f5c36037316.png"}, "summoner_spells": [{"id": 134, "name": "Flash"}, {"id": 129, "name": "Barrier"}]}, "jun": {"id": 7694, "name": "DoubleAiM", "level": 12, "cs": 150, "assists": 2, "deaths": 3, "kills": 2, "champion": {"id": 3666, "name": "Volibear", "slug": "Volibear", "image_url": "https://cdn-api.pandascore.co/images/lol/champion/image/73e72749-ceae-4413-adce-6c1cb863878b.png"}, "summoner_spells": [{"id": 138, "name": "Smite"}, {"id": 134, "name": "Flash"}]}, "mid": {"id": 28790, "name": "Sintax", "level": 13, "cs": 165, "assists": 3, "deaths": 5, "kills": 3, "champion": {"id": 3645, "name": "Taliyah", "slug": "Taliyah", "image_url": "https://cdn-api.pandascore.co/images/lol/champion/image/8fe859d9-af95-4e21-8b1d-9c7c061cd4d2.png"}, "summoner_spells": [{"id": 139, "name": "Teleport"}, {"id": 134, "name": "Flash"}]}, "sup": {"id": 39205, "name": "Lauxio", "level": 9, "cs": 30, "assists": 6, "deaths": 3, "kills": 0, "champion": {"id": 3602, "name": "Nautilus", "slug": "Nautilus", "image_url": "https://cdn-api.pandascore.co/images/lol/champion/image/7f3bc843-2a30-4e14-9cfa-0d8895d2dec4.png"}, "summoner_spells": [{"id": 134, "name": "Flash"}, {"id": 132, "name": "Ignite"}]}, "top": {"id": 37550, "name": "Falleo", "level": 13, "cs": 165, "assists": 1, "deaths": 5, "kills": 2, "champion": {"id": 3703, "name": "Ambessa", "slug": "Ambessa", "image_url": "https://cdn-api.pandascore.co/images/lol/champion/image/4bdc24eb-fcfe-4c11-859e-c76d173aa313.png"}, "summoner_spells": [{"id": 139, "name": "Teleport"}, {"id": 134, "name": "Flash"}]}}, "atakhans": 0, "drakes": 0, "gold": 35969, "heralds": 0, "inhibitors": 0, "nashors": 0, "towers": 0, "voidgrubs": 3, "acronym": "B5"}, "red": {"id": 3340, "name": "Crvena zvezda Esports", "kills": 20, "score": 0, "players": {"adc": {"id": 54354, "name": "Devn", "level": 12, "cs": 183, "assists": 4, "deaths": 1, "kills": 2, "champion": {"id": 3745, "name": "Ezreal", "slug": "Ezreal", "image_url": "https://cdn-api.pandascore.co/images/lol/champion/image/65d28a53-5758-4db1-9d66-d0b68f016ed9.png"}, "summoner_spells": [{"id": 134, "name": "Flash"}, {"id": 129, "name": "Barrier"}]}, "jun": {"id": 32803, "name": "Xeonerr", "level": 12, "cs": 132, "assists": 5, "deaths": 1, "kills": 6, "champion": {"id": 3662, "name": "Vi", "slug": "Vi", "image_url": "https://cdn-api.pandascore.co/images/lol/champion/image/f0e9915e-5f2e-44e9-956d-7b24f4757557.png"}, "summoner_spells": [{"id": 138, "name": "Smite"}, {"id": 134, "name": "Flash"}]}, "mid": {"id": 42195, "name": "Pesho", "level": 15, "cs": 223, "assists": 2, "deaths": 2, "kills": 7, "champion": {"id": 3525, "name": "Aurora", "slug": "Aurora", "image_url": "https://cdn-api.pandascore.co/images/lol/champion/image/fccc9fa8-4ad1-411f-92a0-d43c7b0fc2a0.png"}, "summoner_spells": [{"id": 139, "name": "Teleport"}, {"id": 134, "name": "Flash"}]}, "sup": {"id": 53381, "name": "Zeko", "level": 10, "cs": 22, "assists": 8, "deaths": 3, "kills": 1, "champion": {"id": 3736, "name": "Rell", "slug": "Rell", "image_url": "https://cdn-api.pandascore.co/images/lol/champion/image/04527f37-6ed1-4806-89df-40499a301a24.png"}, "summoner_spells": [{"id": 134, "name": "Flash"}, {"id": 132, "name": "Ignite"}]}, "top": {"id": 52593, "name": "Nenad", "level": 14, "cs": 186, "assists": 1, "deaths": 2, "kills": 4, "champion": {"id": 3630, "name": "Sett", "slug": "Sett", "image_url": "https://cdn-api.pandascore.co/images/lol/champion/image/64d77820-dd57-4ccc-aec1-0492a3e1a74a.png"}, "summoner_spells": [{"id": 139, "name": "Teleport"}, {"id": 134, "name": "Flash"}]}}, "atakhans": 0, "drakes": 3, "gold": 43453, "heralds": 1, "inhibitors": 0, "nashors": 0, "towers": 5, "voidgrubs": 3, "acronym": "CZV"}, "match_id": 1158731, "game_id": 267495, "tournament_id": 16465, "current_timestamp": 1260}, {"blue": {"id": 134408, "name": "BeFive", "kills": 9, "score": 0, "players": {"adc": {"id": 18049, "name": "Pl0x", "level": 11, "cs": 177, "assists": 3, "deaths": 5, "kills": 2, "champion": {"id": 3728, "name": "Varus", "slug": "Varus", "image_url": "https://cdn-api.pandascore.co/images/lol/champion/image/b692cde6-0b60-4900-86f3-4f5c36037316.png"}, "summoner_spells": [{"id": 134, "name": "Flash"}, {"id": 129, "name": "Barrier"}]}, "jun": {"id": 7694, "name": "DoubleAiM", "level": 12, "cs": 150, "assists": 2, "deaths": 4, "kills": 2, "champion": {"id": 3666, "name": "Volibear", "slug": "Volibear", "image_url": "https://cdn-api.pandascore.co/images/lol/champion/image/73e72749-ceae-4413-adce-6c1cb863878b.png"}, "summoner_spells": [{"id": 138, "name": "Smite"}, {"id": 134, "name": "Flash"}]}, "mid": {"id": 28790, "name": "Sintax", "level": 13, "cs": 165, "assists": 3, "deaths": 6, "kills": 3, "champion": {"id": 3645, "name": "Taliyah", "slug": "Taliyah", "image_url": "https://cdn-api.pandascore.co/images/lol/champion/image/8fe859d9-af95-4e21-8b1d-9c7c061cd4d2.png"}, "summoner_spells": [{"id": 139, "name": "Teleport"}, {"id": 134, "name": "Flash"}]}, "sup": {"id": 39205, "name": "Lauxio", "level": 9, "cs": 30, "assists": 6, "deaths": 4, "kills": 0, "champion": {"id": 3602, "name": "Nautilus", "slug": "Nautilus", "image_url": "https://cdn-api.pandascore.co/images/lol/champion/image/7f3bc843-2a30-4e14-9cfa-0d8895d2dec4.png"}, "summoner_spells": [{"id": 134, "name": "Flash"}, {"id": 132, "name": "Ignite"}]}, "top": {"id": 37550, "name": "Falleo", "level": 13, "cs": 165, "assists": 1, "deaths": 5, "kills": 2, "champion": {"id": 3703, "name": "Ambessa", "slug": "Ambessa", "image_url": "https://cdn-api.pandascore.co/images/lol/champion/image/4bdc24eb-fcfe-4c11-859e-c76d173aa313.png"}, "summoner_spells": [{"id": 139, "name": "Teleport"}, {"id": 134, "name": "Flash"}]}}, "atakhans": 0, "drakes": 0, "gold": 36488, "heralds": 0, "inhibitors": 0, "nashors": 0, "towers": 0, "voidgrubs": 3, "acronym": "B5"}, "red": {"id": 3340, "name": "Crvena zvezda Esports", "kills": 24, "score": 0, "players": {"adc": {"id": 54354, "name": "Devn", "level": 13, "cs": 192, "assists": 6, "deaths": 1, "kills": 2, "champion": {"id": 3745, "name": "Ezreal", "slug": "Ezreal", "image_url": "https://cdn-api.pandascore.co/images/lol/champion/image/65d28a53-5758-4db1-9d66-d0b68f016ed9.png"}, "summoner_spells": [{"id": 134, "name": "Flash"}, {"id": 129, "name": "Barrier"}]}, "jun": {"id": 32803, "name": "Xeonerr", "level": 13, "cs": 136, "assists": 7, "deaths": 1, "kills": 7, "champion": {"id": 3662, "name": "Vi", "slug": "Vi", "image_url": "https://cdn-api.pandascore.co/images/lol/champion/image/f0e9915e-5f2e-44e9-956d-7b24f4757557.png"}, "summoner_spells": [{"id": 138, "name": "Smite"}, {"id": 134, "name": "Flash"}]}, "mid": {"id": 42195, "name": "Pesho", "level": 15, "cs": 228, "assists": 3, "deaths": 2, "kills": 10, "champion": {"id": 3525, "name": "Aurora", "slug": "Aurora", "image_url": "https://cdn-api.pandascore.co/images/lol/champion/image/fccc9fa8-4ad1-411f-92a0-d43c7b0fc2a0.png"}, "summoner_spells": [{"id": 139, "name": "Teleport"}, {"id": 134, "name": "Flash"}]}, "sup": {"id": 53381, "name": "Zeko", "level": 11, "cs": 22, "assists": 12, "deaths": 3, "kills": 1, "champion": {"id": 3736, "name": "Rell", "slug": "Rell", "image_url": "https://cdn-api.pandascore.co/images/lol/champion/image/04527f37-6ed1-4806-89df-40499a301a24.png"}, "summoner_spells": [{"id": 134, "name": "Flash"}, {"id": 132, "name": "Ignite"}]}, "top": {"id": 52593, "name": "Nenad", "level": 14, "cs": 195, "assists": 4, "deaths": 2, "kills": 4, "champion": {"id": 3630, "name": "Sett", "slug": "Sett", "image_url": "https://cdn-api.pandascore.co/images/lol/champion/image/64d77820-dd57-4ccc-aec1-0492a3e1a74a.png"}, "summoner_spells": [{"id": 139, "name": "Teleport"}, {"id": 134, "name": "Flash"}]}}, "atakhans": 0, "drakes": 3, "gold": 48005, "heralds": 1, "inhibitors": 1, "nashors": 0, "towers": 9, "voidgrubs": 3, "acronym": "CZV"}, "match_id": 1158731, "game_id": 267495, "tournament_id": 16465, "current_timestamp": 1309}]